Workbook

Sheet README
B1: Brand-to-Balance-Sheet (BBS) valuation model: NVIDIA and Meta Platforms
B2: Brand-to-Balance-Sheet (BBS) method by Jay Nair · github.com/jay-nair-builds/toolkit
B3: Prices at close on 18 Sep 2026, USD billions unless stated. Education only: not personalised investment advice and not a recommendation to buy, sell or hold.
B5: HOW THE MODEL WORKS (story, numbers, value)
B6: 1. Story: each scenario starts with a short narrative of how the business evolves (Bear, Base, Bull, and Market-implied).
B7: 2. Numbers: the story is converted into five explicit years of revenue growth, operating margin and cash conversion; years 6-10 fade growth to a long-run rate.
B8: 3. Value: free cash flow to the firm (FCFF) is discounted at the cost of capital, a terminal value is added, cash is added and debt deducted, then divided by shares.
B9: 4. Reverse DCF: the Market-implied case scales the Base growth rates until value per share equals today's price, showing what the market is assuming.
B10: 5. Score: the BBS sheet scores five pillars (brand power, growth, profit quality, balance sheet, valuation) out of 100. Valuation is formula-driven from this model.
B12: COLOUR CODE
B13: Blue text = input you can change. Black text = formula. Green text = link to another sheet. Yellow fill = key assumption to stress-test first.
B15: SHEETS
... B29: StockAnalysis.com NVDA and META statistics pages; NVIDIA and Meta earnings releases (fiscal-year results FY2017-FY2026 and 2016-2025, and Q2 2026); FactSet Earnings Insight (18 Sep 2026); iShares SOXX and SPDR XLC fact sheets; Federal Reserve H.15; BLS CPI; BEA personal income; University of Michigan; SIA; TMT Finance.

Sheet Summary
A1: Summary: NVIDIA vs Meta Platforms
A2: All values link to the company sheets. USD; prices at close 18 Sep 2026. Education only.
A3: Brand-to-Balance-Sheet (BBS) method by Jay Nair · github.com/jay-nair-builds/toolkit
A4: Overview
A5: Item | B5: NVDA | C5: META
A6: Share price ($) | B6: =NVDA!B5 -> 222.27 | C6: =META!B5 -> 665.75
A7: WACC used | B7: =NVDA!B27 -> 0.11 | C7: =META!B27 -> 0.098366094
A8: Value per share: Bear ($) | B8: =NVDA!C58 -> 55.763547 | C8: =META!C58 -> 201.50359
A9: Value per share: Base ($) | B9: =NVDA!D58 -> 141.62346 | C9: =META!D58 -> 456.84318
A10: Value per share: Bull ($) | B10: =NVDA!E58 -> 238.70365 | C10: =META!E58 -> 722.46178
A11: Value per share: Market-implied ($) | B11: =NVDA!F58 -> 222.26808 | C11: =META!F58 -> 665.74355
A12: Base value versus price | B12: =NVDA!D60 -> -0.36283144 | C12: =META!D60 -> -0.3137917
A13: Revenue CAGR to year 5: Base | B13: =NVDA!D64 -> 0.21520441 | C13: =META!D64 -> 0.11830539
A14: Revenue CAGR to year 5: priced in | B14: =NVDA!F64 -> 0.31781823 | C14: =META!F64 -> 0.18730608
A15: Terminal value share of EV: Base | B15: =NVDA!D61 -> 0.51116769 | C15: =META!D61 -> 0.57973492
A16: Implied terminal return on capital: Base | B16: =NVDA!D63 -> 0.15 | C16: =META!D63 -> 0.12
A17: BBS Score (0-100) | B17: =BBS_Score!B13 -> 78 | C17: =BBS_Score!C13 -> 56
A19: Read-out: a Base value below the price means the price assumes more than the Base story, under these assumptions. Change the yellow cells on each company sheet to test that.
A21: Multiples and benchmarks
A22: Item | B22: NVDA | C22: META
A23: Forward P/E (consensus) | B23: =PE_Benchmarks!B10 -> 18.45 | C23: =PE_Benchmarks!C10 -> 20.57
A24: S&P 500 forward P/E | B24: =PE_Benchmarks!B18 -> 19.1 | C24: =PE_Benchmarks!B18 -> 19.1
A25: Industry trailing P/E | B25: =PE_Benchmarks!B27 -> 61.52 | C25: =PE_Benchmarks!C27 -> 15.5
A26: P/E implied by Base value | B26: =PE_Benchmarks!B41 -> 11.75576 | C26: =PE_Benchmarks!C41 -> 14.115305
A27: Revenue CAGR, last 5 years | B27: =NVDA_PnL!B50 -> 0.66898582 | C27: =META_PnL!B50 -> 0.18511415
A28: Revenue CAGR, LTM to forecast year 5 (Base) | B28: =NVDA_PnL!B52 -> 0.21520441 | C28: =META_PnL!B52 -> 0.11830833

Sheet NVDA
A1: NVIDIA (NVDA): intrinsic value build (story, numbers, value)
A2: USD billions unless stated. Prices at close 18 Sep 2026. Blue = input, black = formula, yellow fill = key assumption.
A4: 1. Market data
A5: Share price ($) | B5: 222.27
A6: Market capitalisation ($bn) | B6: 5370
A7: Shares outstanding (bn) | B7: =B6/B5 -> 24.159806
A8: Cash ($bn) | B8: 62.47
A9: Total debt ($bn) | B9: 38.86
A10: Revenue, last 12 months ($bn) | B10: 302.97
A11: Tax rate on operating profit | B11: 0.15
A13: 2. Cost of capital (build-up)
A14: Risk-free rate | B14: 0.0494
A15: Equity risk premium | B15: 0.045
A16: Raw beta | B16: 2.22
A17: Blume weight on raw beta | B17: 0.67
A18: Adjusted beta | B18: =B17*B16+(1-B17)*1 -> 1.8174
A19: Cost of equity | B19: =B14+B18*B15 -> 0.131183
A20: Pre-tax cost of debt | B20: 0.0575
A21: After-tax cost of debt | B21: =B20*(1-B11) -> 0.048875
A22: Equity weight (market cap / (market cap + debt)) | B22: =B6/(B6+B9) -> 0.99281549
A23: Debt weight | B23: =B9/(B6+B9) -> 0.0071845084
A24: WACC (calculated) | B24: =B22*B19+B23*B21 -> 0.13059166
A25: WACC floor | B25: 0.08
A26: WACC cap | B26: 0.11
A27: WACC used | B27: =MEDIAN(B25,B24,B26) -> 0.11
A28: Terminal growth rate | B28: 0.03
A29: Growth fades to (years 6-10) | B29: 0.03
A31: 3. Story to numbers: scenario assumptions
A32: Driver | B32: Unit | C32: Bear | D32: Base | E32: Bull | F32: Market-implied
A33: Story: Bear | B33: AI infrastructure spending digests: revenue holds near $400B in year 1, then falls as customers pause orders and custom chips take share. Margins compress toward 45%.
A34: Story: Base | B34: The build-out continues but decelerates: after a year-1 revenue of about $450B, growth of 25%, 18%, 12% and 8% follows, while margins fade from 62% to 55% as competition rises.
A35: Story: Bull | B35: Demand compounds: revenue passes $1.1 trillion by year 5 with margins above 60%, and the platform stays the industry standard.
A36: Story: Market-implied | B36: What today's price requires: the Base story with growth in years 2-5 scaled up until value per share equals the price (see the scale factor in F47).
A38: Year-1 revenue (next 12 months) | B38: $bn | C38: 400 | D38: 450 | E38: 500 | F38: =D38 -> 450
A39: Revenue growth, year 2 | B39: % | C39: 0.05 | D39: 0.25 | E39: 0.35 | F39: =D39*$F$47 -> 0.451025
A40: Revenue growth, year 3 | B40: % | C40: -0.1 | D40: 0.18 | E40: 0.25 | F40: =D40*$F$47 -> 0.324738
A41: Revenue growth, year 4 | B41: % | C41: 0 | D41: 0.12 | E41: 0.18 | F41: =D41*$F$47 -> 0.216492
A42: Revenue growth, year 5 | B42: % | C42: 0.03 | D42: 0.08 | E42: 0.12 | F42: =D42*$F$47 -> 0.144328
A43: Operating margin, year 1 | B43: % | C43: 0.55 | D43: 0.62 | E43: 0.65 | F43: =D43 -> 0.62
A44: Operating margin, year 5 (held to year 10) | B44: % | C44: 0.45 | D44: 0.55 | E44: 0.62 | F44: =D44 -> 0.55
A45: Cash conversion, year 1 (FCFF / after-tax operating profit) | B45: % | C45: 0.75 | D45: 0.75 | E45: 0.75 | F45: =D45 -> 0.75
A46: Cash conversion, year 5 (held to year 10) | B46: % | C46: 0.75 | D46: 0.8 | E46: 0.85 | F46: =D46 -> 0.8
A47: Growth scale factor (Market-implied only) | B47: x | C47: 1 | D47: 1 | E47: 1 | F47: 1.8041 | G47: Goal Seek F58 to equal B5 by changing F47
A49: 4. Valuation summary
A50: Item | B50: Unit | C50: Bear | D50: Base | E50: Bull | F50: Market-implied
A51: PV of FCFF, years 1-10 | B51: $bn | C51: =SUM(C77:L77) -> 736.50859 | D51: =SUM(C91:L91) -> 1661.0449 | E51: =SUM(C105:L105) -> 2630.0776 | F51: =SUM(C119:L119) -> 2411.3768
A52: Terminal value at year 10 | B52: $bn | C52: =L75*(1+$B$28)/($B$27-$B$28) -> 1667.0748 | D52: =L89*(1+$B$28)/($B$27-$B$28) -> 4931.9045 | E52: =L103*(1+$B$28)/($B$27-$B$28) -> 8840.1001 | F52: =L117*(1+$B$28)/($B$27-$B$28) -> 8333.6066
A53: PV of terminal value | B53: $bn | C53: =C52*L76 -> 587.11787 | D53: =D52*L90 -> 1736.9402 | E53: =E52*L104 -> 3113.346 | F53: =F52*L118 -> 2934.9669
A54: Enterprise value (operating assets) | B54: $bn | C54: =C51+C53 -> 1323.6265 | D54: =D51+D53 -> 3397.9852 | E54: =E51+E53 -> 5743.4237 | F54: =F51+F53 -> 5346.3437
A55: Plus: cash | B55: $bn | C55: =$B$8 -> 62.47 | D55: =$B$8 -> 62.47 | E55: =$B$8 -> 62.47 | F55: =$B$8 -> 62.47
A56: Less: debt | B56: $bn | C56: =-$B$9 -> -38.86 | D56: =-$B$9 -> -38.86 | E56: =-$B$9 -> -38.86 | F56: =-$B$9 -> -38.86
A57: Equity value | B57: $bn | C57: =C54+C55+C56 -> 1347.2365 | D57: =D54+D55+D56 -> 3421.5952 | E57: =E54+E55+E56 -> 5767.0337 | F57: =F54+F55+F56 -> 5369.9537
A58: Value per share | B58: $ | C58: =C57/$B$7 -> 55.763547 | D58: =D57/$B$7 -> 141.62346 | E58: =E57/$B$7 -> 238.70365 | F58: =F57/$B$7 -> 222.26808
A59: Share price | B59: $ | C59: =$B$5 -> 222.27 | D59: =$B$5 -> 222.27 | E59: =$B$5 -> 222.27 | F59: =$B$5 -> 222.27
A60: Value versus price | B60: % | C60: =C58/C59-1 -> -0.74911798 | D60: =D58/D59-1 -> -0.36283144 | E60: =E58/E59-1 -> 0.073935507 | F60: =F58/F59-1 -> -8.6192407e-06
A61: Terminal value as % of enterprise value | B61: % | C61: =C53/C54 -> 0.44356765 | D61: =D53/D54 -> 0.51116769 | E61: =E53/E54 -> 0.54207146 | F61: =F53/F54 -> 0.54896712
A62: Terminal reinvestment rate (1 - cash conversion) | B62: % | C62: =1-L73 -> 0.25 | D62: =1-L87 -> 0.2 | E62: =1-L101 -> 0.15 | F62: =1-L115 -> 0.2
A63: Implied terminal return on capital (g / reinvestment rate) | B63: % | C63: =IF(C62>0,$B$28/C62,0) -> 0.12 | D63: =IF(D62>0,$B$28/D62,0) -> 0.15 | E63: =IF(E62>0,$B$28/E62,0) -> 0.2 | F63: =IF(F62>0,$B$28/F62,0) -> 0.15
A64: Revenue CAGR, last 12 months to year 5 | B64: % | C64: =(G68/$B$10)^(1/5)-1 -> 0.051443352 | D64: =(G82/$B$10)^(1/5)-1 -> 0.21520441 | E64: =(G96/$B$10)^(1/5)-1 -> 0.2977255 | F64: =(G110/$B$10)^(1/5)-1 -> 0.31781823
A65: 5. Cash-flow projections (FCFF) by scenario
A66: Bear scenario
A67: Year | C67: 1 | D67: 2 | E67: 3 | F67: 4 | G67: 5 | H67: 6 | I67: 7 | J67: 8 | K67: 9 | L67: 10
A68: Revenue ($bn) | C68: =C$38 -> 400 | D68: =C68*(1+D69) -> 420 | E68: =D68*(1+E69) -> 378 | F68: =E68*(1+F69) -> 378 | G68: =F68*(1+G69) -> 389.34 | H68: =G68*(1+H69) -> 401.0202 | I68: =H68*(1+I69) -> 413.05081 | J68: =I68*(1+J69) -> 425.44233 | K68: =J68*(1+K69) -> 438.2056 | L68: =K68*(1+L69) -> 451.35177
A69: Revenue growth | C69: =C68/$B$10-1 -> 0.32026273 | D69: =C$39 -> 0.05 | E69: =C$40 -> -0.1 | F69: =C$41 -> 0 | G69: =C$42 -> 0.03 | H69: =G69+($B$29-$G69)/5 -> 0.03 | I69: =H69+($B$29-$G69)/5 -> 0.03 | J69: =I69+($B$29-$G69)/5 -> 0.03 | K69: =J69+($B$29-$G69)/5 -> 0.03 | L69: =K69+($B$29-$G69)/5 -> 0.03
A70: Operating margin | C70: =C$43+(C$44-C$43)*MIN(C$67-1,4)/4 -> 0.55 | D70: =C$43+(C$44-C$43)*MIN(D$67-1,4)/4 -> 0.525 | E70: =C$43+(C$44-C$43)*MIN(E$67-1,4)/4 -> 0.5 | F70: =C$43+(C$44-C$43)*MIN(F$67-1,4)/4 -> 0.475 | G70: =C$43+(C$44-C$43)*MIN(G$67-1,4)/4 -> 0.45 | H70: =C$43+(C$44-C$43)*MIN(H$67-1,4)/4 -> 0.45 | I70: =C$43+(C$44-C$43)*MIN(I$67-1,4)/4 -> 0.45 | J70: =C$43+(C$44-C$43)*MIN(J$67-1,4)/4 -> 0.45 | K70: =C$43+(C$44-C$43)*MIN(K$67-1,4)/4 -> 0.45 | L70: =C$43+(C$44-C$43)*MIN(L$67-1,4)/4 -> 0.45
A71: Operating profit (EBIT) | C71: =C68*C70 -> 220 | D71: =D68*D70 -> 220.5 | E71: =E68*E70 -> 189 | F71: =F68*F70 -> 179.55 | G71: =G68*G70 -> 175.203 | H71: =H68*H70 -> 180.45909 | I71: =I68*I70 -> 185.87286 | J71: =J68*J70 -> 191.44905 | ... L71: =L68*L70 -> 203.1083
A72: After-tax operating profit | C72: =C71*(1-$B$11) -> 187 | D72: =D71*(1-$B$11) -> 187.425 | E72: =E71*(1-$B$11) -> 160.65 | F72: =F71*(1-$B$11) -> 152.6175 | G72: =G71*(1-$B$11) -> 148.92255 | H72: =H71*(1-$B$11) -> 153.39023 | I72: =I71*(1-$B$11) -> 157.99193 | J72: =J71*(1-$B$11) -> 162.73169 | ... L72: =L71*(1-$B$11) -> 172.64205
A73: Cash conversion | C73: =C$45+(C$46-C$45)*MIN(C$67-1,4)/4 -> 0.75 | D73: =C$45+(C$46-C$45)*MIN(D$67-1,4)/4 -> 0.75 | E73: =C$45+(C$46-C$45)*MIN(E$67-1,4)/4 -> 0.75 | F73: =C$45+(C$46-C$45)*MIN(F$67-1,4)/4 -> 0.75 | G73: =C$45+(C$46-C$45)*MIN(G$67-1,4)/4 -> 0.75 | H73: =C$45+(C$46-C$45)*MIN(H$67-1,4)/4 -> 0.75 | I73: =C$45+(C$46-C$45)*MIN(I$67-1,4)/4 -> 0.75 | J73: =C$45+(C$46-C$45)*MIN(J$67-1,4)/4 -> 0.75 | K73: =C$45+(C$46-C$45)*MIN(K$67-1,4)/4 -> 0.75 | L73: =C$45+(C$46-C$45)*MIN(L$67-1,4)/4 -> 0.75
A74: Reinvestment | C74: =C72*(1-C73) -> 46.75 | D74: =D72*(1-D73) -> 46.85625 | E74: =E72*(1-E73) -> 40.1625 | F74: =F72*(1-F73) -> 38.154375 | G74: =G72*(1-G73) -> 37.230638 | H74: =H72*(1-H73) -> 38.347557 | I74: =I72*(1-I73) -> 39.497983 | J74: =J72*(1-J73) -> 40.682923 | ... L74: =L72*(1-L73) -> 43.160513
A75: Free cash flow to firm (FCFF) | C75: =C72-C74 -> 140.25 | D75: =D72-D74 -> 140.56875 | E75: =E72-E74 -> 120.4875 | F75: =F72-F74 -> 114.46313 | G75: =G72-G74 -> 111.69191 | H75: =H72-H74 -> 115.04267 | I75: =I72-I74 -> 118.49395 | J75: =J72-J74 -> 122.04877 | ... L75: =L72-L74 -> 129.48154
A76: Discount factor | C76: =1/(1+$B$27)^C$67 -> 0.9009009 | D76: =1/(1+$B$27)^D$67 -> 0.81162243 | E76: =1/(1+$B$27)^E$67 -> 0.73119138 | F76: =1/(1+$B$27)^F$67 -> 0.65873097 | G76: =1/(1+$B$27)^G$67 -> 0.59345133 | H76: =1/(1+$B$27)^H$67 -> 0.53464084 | I76: =1/(1+$B$27)^I$67 -> 0.48165841 | J76: =1/(1+$B$27)^J$67 -> 0.4339265 | ... L76: =1/(1+$B$27)^L$67 -> 0.35218448
A77: Present value of FCFF | C77: =C75*C76 -> 126.35135 | D77: =D75*D76 -> 114.08875 | E77: =E75*E76 -> 88.099422 | F77: =F75*F76 -> 75.400406 | G77: =G75*G76 -> 66.283714 | H77: =H75*H76 -> 61.506509 | I77: =I75*I76 -> 57.073608 | J77: =J75*J76 -> 52.960194 | ... L77: =L75*L76 -> 45.601388
A80: Base scenario
A81: Year | C81: 1 | D81: 2 | E81: 3 | F81: 4 | G81: 5 | H81: 6 | I81: 7 | J81: 8 | K81: 9 | L81: 10
A82: Revenue ($bn) | C82: =D$38 -> 450 | D82: =C82*(1+D83) -> 562.5 | E82: =D82*(1+E83) -> 663.75 | F82: =E82*(1+F83) -> 743.4 | G82: =F82*(1+G83) -> 802.872 | H82: =G82*(1+H83) -> 859.07304 | I82: =H82*(1+I83) -> 910.61742 | J82: =I82*(1+J83) -> 956.14829 | K82: =J82*(1+K83) -> 994.39423 | L82: =K82*(1+L83) -> 1024.2261
A83: Revenue growth | C83: =C82/$B$10-1 -> 0.48529557 | D83: =D$39 -> 0.25 | E83: =D$40 -> 0.18 | F83: =D$41 -> 0.12 | G83: =D$42 -> 0.08 | H83: =G83+($B$29-$G83)/5 -> 0.07 | I83: =H83+($B$29-$G83)/5 -> 0.06 | J83: =I83+($B$29-$G83)/5 -> 0.05 | K83: =J83+($B$29-$G83)/5 -> 0.04 | L83: =K83+($B$29-$G83)/5 -> 0.03
A84: Operating margin | C84: =D$43+(D$44-D$43)*MIN(C$81-1,4)/4 -> 0.62 | D84: =D$43+(D$44-D$43)*MIN(D$81-1,4)/4 -> 0.6025 | E84: =D$43+(D$44-D$43)*MIN(E$81-1,4)/4 -> 0.585 | F84: =D$43+(D$44-D$43)*MIN(F$81-1,4)/4 -> 0.5675 | G84: =D$43+(D$44-D$43)*MIN(G$81-1,4)/4 -> 0.55 | H84: =D$43+(D$44-D$43)*MIN(H$81-1,4)/4 -> 0.55 | I84: =D$43+(D$44-D$43)*MIN(I$81-1,4)/4 -> 0.55 | J84: =D$43+(D$44-D$43)*MIN(J$81-1,4)/4 -> 0.55 | K84: =D$43+(D$44-D$43)*MIN(K$81-1,4)/4 -> 0.55 | L84: =D$43+(D$44-D$43)*MIN(L$81-1,4)/4 -> 0.55
A85: Operating profit (EBIT) | C85: =C82*C84 -> 279 | D85: =D82*D84 -> 338.90625 | E85: =E82*E84 -> 388.29375 | F85: =F82*F84 -> 421.8795 | G85: =G82*G84 -> 441.5796 | H85: =H82*H84 -> 472.49017 | I85: =I82*I84 -> 500.83958 | J85: =J82*J84 -> 525.88156 | ... L85: =L82*L84 -> 563.32433
A86: After-tax operating profit | C86: =C85*(1-$B$11) -> 237.15 | D86: =D85*(1-$B$11) -> 288.07031 | E86: =E85*(1-$B$11) -> 330.04969 | F86: =F85*(1-$B$11) -> 358.59758 | G86: =G85*(1-$B$11) -> 375.34266 | H86: =H85*(1-$B$11) -> 401.61665 | I86: =I85*(1-$B$11) -> 425.71364 | J86: =J85*(1-$B$11) -> 446.99933 | ... L86: =L85*(1-$B$11) -> 478.82568
A87: Cash conversion | C87: =D$45+(D$46-D$45)*MIN(C$81-1,4)/4 -> 0.75 | D87: =D$45+(D$46-D$45)*MIN(D$81-1,4)/4 -> 0.7625 | E87: =D$45+(D$46-D$45)*MIN(E$81-1,4)/4 -> 0.775 | F87: =D$45+(D$46-D$45)*MIN(F$81-1,4)/4 -> 0.7875 | G87: =D$45+(D$46-D$45)*MIN(G$81-1,4)/4 -> 0.8 | H87: =D$45+(D$46-D$45)*MIN(H$81-1,4)/4 -> 0.8 | I87: =D$45+(D$46-D$45)*MIN(I$81-1,4)/4 -> 0.8 | J87: =D$45+(D$46-D$45)*MIN(J$81-1,4)/4 -> 0.8 | K87: =D$45+(D$46-D$45)*MIN(K$81-1,4)/4 -> 0.8 | L87: =D$45+(D$46-D$45)*MIN(L$81-1,4)/4 -> 0.8
A88: Reinvestment | C88: =C86*(1-C87) -> 59.2875 | D88: =D86*(1-D87) -> 68.416699 | E88: =E86*(1-E87) -> 74.26118 | F88: =F86*(1-F87) -> 76.201985 | G88: =G86*(1-G87) -> 75.068532 | H88: =H86*(1-H87) -> 80.323329 | I88: =I86*(1-I87) -> 85.142729 | J88: =J86*(1-J87) -> 89.399865 | ... L88: =L86*(1-L87) -> 95.765136
A89: Free cash flow to firm (FCFF) | C89: =C86-C88 -> 177.8625 | D89: =D86-D88 -> 219.65361 | E89: =E86-E88 -> 255.78851 | F89: =F86-F88 -> 282.39559 | G89: =G86-G88 -> 300.27413 | H89: =H86-H88 -> 321.29332 | I89: =I86-I88 -> 340.57092 | J89: =J86-J88 -> 357.59946 | ... L89: =L86-L88 -> 383.06054
A90: Discount factor | C90: =1/(1+$B$27)^C$81 -> 0.9009009 | D90: =1/(1+$B$27)^D$81 -> 0.81162243 | E90: =1/(1+$B$27)^E$81 -> 0.73119138 | F90: =1/(1+$B$27)^F$81 -> 0.65873097 | G90: =1/(1+$B$27)^G$81 -> 0.59345133 | H90: =1/(1+$B$27)^H$81 -> 0.53464084 | I90: =1/(1+$B$27)^I$81 -> 0.48165841 | J90: =1/(1+$B$27)^J$81 -> 0.4339265 | ... L90: =1/(1+$B$27)^L$81 -> 0.35218448
A91: Present value of FCFF | C91: =C89*C90 -> 160.23649 | D91: =D89*D90 -> 178.2758 | E91: =E89*E90 -> 187.03035 | F91: =F89*F90 -> 186.02272 | G91: =G89*G90 -> 178.19808 | H91: =H89*H90 -> 171.77653 | I91: =I89*I90 -> 164.03885 | J91: =J89*J90 -> 155.17188 | ... L91: =L89*L90 -> 134.90798
A94: Bull scenario
A95: Year | C95: 1 | D95: 2 | E95: 3 | F95: 4 | G95: 5 | H95: 6 | I95: 7 | J95: 8 | K95: 9 | L95: 10
A96: Revenue ($bn) | C96: =E$38 -> 500 | D96: =C96*(1+D97) -> 675 | E96: =D96*(1+E97) -> 843.75 | F96: =E96*(1+F97) -> 995.625 | G96: =F96*(1+G97) -> 1115.1 | H96: =G96*(1+H97) -> 1228.8402 | I96: =H96*(1+I97) -> 1332.0628 | J96: =I96*(1+J97) -> 1419.9789 | K96: =J96*(1+K97) -> 1488.1379 | L96: =K96*(1+L97) -> 1532.782
A97: Revenue growth | C97: =C96/$B$10-1 -> 0.65032842 | D97: =E$39 -> 0.35 | E97: =E$40 -> 0.25 | F97: =E$41 -> 0.18 | G97: =E$42 -> 0.12 | H97: =G97+($B$29-$G97)/5 -> 0.102 | I97: =H97+($B$29-$G97)/5 -> 0.084 | J97: =I97+($B$29-$G97)/5 -> 0.066 | K97: =J97+($B$29-$G97)/5 -> 0.048 | L97: =K97+($B$29-$G97)/5 -> 0.03
A98: Operating margin | C98: =E$43+(E$44-E$43)*MIN(C$95-1,4)/4 -> 0.65 | D98: =E$43+(E$44-E$43)*MIN(D$95-1,4)/4 -> 0.6425 | E98: =E$43+(E$44-E$43)*MIN(E$95-1,4)/4 -> 0.635 | F98: =E$43+(E$44-E$43)*MIN(F$95-1,4)/4 -> 0.6275 | G98: =E$43+(E$44-E$43)*MIN(G$95-1,4)/4 -> 0.62 | H98: =E$43+(E$44-E$43)*MIN(H$95-1,4)/4 -> 0.62 | I98: =E$43+(E$44-E$43)*MIN(I$95-1,4)/4 -> 0.62 | J98: =E$43+(E$44-E$43)*MIN(J$95-1,4)/4 -> 0.62 | K98: =E$43+(E$44-E$43)*MIN(K$95-1,4)/4 -> 0.62 | L98: =E$43+(E$44-E$43)*MIN(L$95-1,4)/4 -> 0.62
A99: Operating profit (EBIT) | C99: =C96*C98 -> 325 | D99: =D96*D98 -> 433.6875 | E99: =E96*E98 -> 535.78125 | F99: =F96*F98 -> 624.75469 | G99: =G96*G98 -> 691.362 | H99: =H96*H98 -> 761.88092 | I99: =I96*I98 -> 825.87892 | J99: =J96*J98 -> 880.38693 | ... L99: =L96*L98 -> 950.32487
A100: After-tax operating profit | C100: =C99*(1-$B$11) -> 276.25 | D100: =D99*(1-$B$11) -> 368.63437 | E100: =E99*(1-$B$11) -> 455.41406 | F100: =F99*(1-$B$11) -> 531.04148 | G100: =G99*(1-$B$11) -> 587.6577 | H100: =H99*(1-$B$11) -> 647.59879 | I100: =I99*(1-$B$11) -> 701.99708 | J100: =J99*(1-$B$11) -> 748.32889 | ... L100: =L99*(1-$B$11) -> 807.77614
A101: Cash conversion | C101: =E$45+(E$46-E$45)*MIN(C$95-1,4)/4 -> 0.75 | D101: =E$45+(E$46-E$45)*MIN(D$95-1,4)/4 -> 0.775 | E101: =E$45+(E$46-E$45)*MIN(E$95-1,4)/4 -> 0.8 | F101: =E$45+(E$46-E$45)*MIN(F$95-1,4)/4 -> 0.825 | G101: =E$45+(E$46-E$45)*MIN(G$95-1,4)/4 -> 0.85 | H101: =E$45+(E$46-E$45)*MIN(H$95-1,4)/4 -> 0.85 | I101: =E$45+(E$46-E$45)*MIN(I$95-1,4)/4 -> 0.85 | J101: =E$45+(E$46-E$45)*MIN(J$95-1,4)/4 -> 0.85 | K101: =E$45+(E$46-E$45)*MIN(K$95-1,4)/4 -> 0.85 | L101: =E$45+(E$46-E$45)*MIN(L$95-1,4)/4 -> 0.85
A102: Reinvestment | C102: =C100*(1-C101) -> 69.0625 | D102: =D100*(1-D101) -> 82.942734 | E102: =E100*(1-E101) -> 91.082813 | F102: =F100*(1-F101) -> 92.93226 | G102: =G100*(1-G101) -> 88.148655 | H102: =H100*(1-H101) -> 97.139818 | I102: =I100*(1-I101) -> 105.29956 | J102: =J100*(1-J101) -> 112.24933 | ... L102: =L100*(1-L101) -> 121.16642
A103: Free cash flow to firm (FCFF) | C103: =C100-C102 -> 207.1875 | D103: =D100-D102 -> 285.69164 | E103: =E100-E102 -> 364.33125 | F103: =F100-F102 -> 438.10922 | G103: =G100-G102 -> 499.50905 | H103: =H100-H102 -> 550.45897 | I103: =I100-I102 -> 596.69752 | J103: =J100-J102 -> 636.07956 | ... L103: =L100-L102 -> 686.60972
A104: Discount factor | C104: =1/(1+$B$27)^C$95 -> 0.9009009 | D104: =1/(1+$B$27)^D$95 -> 0.81162243 | E104: =1/(1+$B$27)^E$95 -> 0.73119138 | F104: =1/(1+$B$27)^F$95 -> 0.65873097 | G104: =1/(1+$B$27)^G$95 -> 0.59345133 | H104: =1/(1+$B$27)^H$95 -> 0.53464084 | I104: =1/(1+$B$27)^I$95 -> 0.48165841 | J104: =1/(1+$B$27)^J$95 -> 0.4339265 | ... L104: =1/(1+$B$27)^L$95 -> 0.35218448
A105: Present value of FCFF | C105: =C103*C104 -> 186.65541 | D105: =D103*D104 -> 231.87374 | E105: =E103*E104 -> 266.39587 | F105: =F103*F104 -> 288.59612 | G105: =G103*G104 -> 296.43431 | H105: =H103*H104 -> 294.29784 | I105: =I103*I104 -> 287.40438 | J105: =J103*J104 -> 276.01177 | ... L105: =L103*L104 -> 241.81329
A108: Market-implied scenario
A109: Year | C109: 1 | D109: 2 | E109: 3 | F109: 4 | G109: 5 | H109: 6 | I109: 7 | J109: 8 | K109: 9 | L109: 10
A110: Revenue ($bn) | C110: =F$38 -> 450 | D110: =C110*(1+D111) -> 652.96125 | E110: =D110*(1+E111) -> 865.00258 | F110: =E110*(1+F111) -> 1052.2687 | G110: =F110*(1+G111) -> 1204.1406 | H110: =G110*(1+H111) -> 1350.3984 | I110: =H110*(1+I111) -> 1483.5433 | J110: =I110*(1+J111) -> 1595.8938 | K110: =J110*(1+K111) -> 1680.2617 | L110: =K110*(1+L111) -> 1730.6696
A111: Revenue growth | C111: =C110/$B$10-1 -> 0.48529557 | D111: =F$39 -> 0.451025 | E111: =F$40 -> 0.324738 | F111: =F$41 -> 0.216492 | G111: =F$42 -> 0.144328 | H111: =G111+($B$29-$G111)/5 -> 0.1214624 | I111: =H111+($B$29-$G111)/5 -> 0.0985968 | J111: =I111+($B$29-$G111)/5 -> 0.0757312 | K111: =J111+($B$29-$G111)/5 -> 0.0528656 | L111: =K111+($B$29-$G111)/5 -> 0.03
...

Sheet NVDA_PnL
A1: NVIDIA: income statement, 10 years of history and 5 forecast periods
A2: USD millions except per-share data. Fiscal years end late January (FY2026 = year ended 25 Jan 2026). Forecast columns are 12-month periods from the valuation date (NTM = next twelve months, to Sep-27) and link to the Base scenario on the NVDA sheet. Blue = input, black = formula, green = link.
A4: Period | B4: FY2017 | C4: FY2018 | D4: FY2019 | E4: FY2020 | F4: FY2021 | G4: FY2022 | H4: FY2023 | I4: FY2024 | J4: FY2025 | K4: FY2026 | L4: TTM Jul-26 | M4: NTM | N4: Year 2 | O4: Year 3 | P4: Year 4 | Q4: Year 5
A5: Period end | B5: Jan-17 | C5: Jan-18 | D5: Jan-19 | E5: Jan-20 | F5: Jan-21 | G5: Jan-22 | H5: Jan-23 | I5: Jan-24 | J5: Jan-25 | K5: Jan-26 | M5: Sep-27 | N5: Sep-28 | O5: Sep-29 | P5: Sep-30 | Q5: Sep-31
A6: Basis | B6: Actual | C6: Actual | D6: Actual | E6: Actual | F6: Actual | G6: Actual | H6: Actual | I6: Actual | J6: Actual | K6: Actual | L6: Latest 12m | M6: Base forecast | N6: Base forecast | O6: Base forecast | P6: Base forecast | Q6: Base forecast
A7: Forecast year | M7: 1 | N7: 2 | O7: 3 | P7: 4 | Q7: 5
A8: Revenue | B8: 6910 | C8: 9714 | D8: 11716 | E8: 10918 | F8: 16675 | G8: 26914 | H8: 26974 | I8: 60922 | J8: 130497 | K8: 215938 | L8: 302970 | M8: =NVDA!C82*1000 -> 450000 | N8: =NVDA!D82*1000 -> 562500 | O8: =NVDA!E82*1000 -> 663750 | P8: =NVDA!F82*1000 -> 743400 | Q8: =NVDA!G82*1000 -> 802872
A9: Revenue growth | C9: =C8/B8-1 -> 0.40578871 | D9: =D8/C8-1 -> 0.2060943 | E9: =E8/D8-1 -> -0.068111984 | F9: =F8/E8-1 -> 0.52729438 | G9: =G8/F8-1 -> 0.61403298 | H9: =H8/G8-1 -> 0.002229323 | I9: =I8/H8-1 -> 1.2585453 | J9: =J8/I8-1 -> 1.1420341 | K9: =K8/J8-1 -> 0.65473536 | M9: =M8/L8-1 -> 0.48529557 | N9: =N8/M8-1 -> 0.25 | O9: =O8/N8-1 -> 0.18 | P9: =P8/O8-1 -> 0.12 | Q9: =Q8/P8-1 -> 0.08
A10: Cost of revenue | B10: 2847 | C10: 3892 | D10: 4545 | E10: 4150 | F10: 6279 | G10: 9439 | H10: 11618 | I10: 16621 | J10: 32639 | K10: 62475 | M10: =M8-M11 -> 121500 | N10: =N8-N11 -> 157500 | O10: =O8-O11 -> 192487.5 | P10: =P8-P11 -> 223020 | Q10: =Q8-Q11 -> 248890.32
A11: Gross profit | B11: =B8-B10 -> 4063 | C11: =C8-C10 -> 5822 | D11: =D8-D10 -> 7171 | E11: =E8-E10 -> 6768 | F11: =F8-F10 -> 10396 | G11: =G8-G10 -> 17475 | H11: =H8-H10 -> 15356 | I11: =I8-I10 -> 44301 | ... K11: =K8-K10 -> 153463 | L11: 226241 | M11: =M8*M12 -> 328500 | N11: =N8*N12 -> 405000 | O11: =O8*O12 -> 471262.5 | P11: =P8*P12 -> 520380 | Q11: =Q8*Q12 -> 553981.68
A12: Gross margin | B12: =B11/B8 -> 0.58798842 | C12: =C11/C8 -> 0.59934116 | D12: =D11/D8 -> 0.61206897 | E12: =E11/E8 -> 0.61989375 | F12: =F11/F8 -> 0.62344828 | G12: =G11/G8 -> 0.64929033 | H12: =H11/H8 -> 0.56928894 | I12: =I11/I8 -> 0.72717573 | ... L12: =L11/L8 -> 0.7467439 | M12: =$B$40+($B$41-$B$40)*(M$7-1)/4 -> 0.73 | N12: =$B$40+($B$41-$B$40)*(N$7-1)/4 -> 0.72 | O12: =$B$40+($B$41-$B$40)*(O$7-1)/4 -> 0.71 | P12: =$B$40+($B$41-$B$40)*(P$7-1)/4 -> 0.7 | Q12: =$B$40+($B$41-$B$40)*(Q$7-1)/4 -> 0.69
A13: Research and development | B13: 1466 | C13: 1797 | D13: 2376 | E13: 2829 | F13: 3924 | G13: 5268 | H13: 7339 | I13: 8675 | J13: 12914 | K13: 18497 | M13: =M16*$B$42 -> 39600 | N13: =N16*$B$42 -> 52875 | O13: =O16*$B$42 -> 66375 | P13: =P16*$B$42 -> 78800.4 | Q13: =Q16*$B$42 -> 89921.664
A14: Sales, general and administrative | B14: 663 | C14: 815 | D14: 991 | E14: 1093 | F14: 1940 | G14: 2166 | H14: 2440 | I14: 2654 | J14: 3491 | K14: 4579 | M14: =M16-M13 -> 9900 | N14: =N16-N13 -> 13218.75 | O14: =O16-O13 -> 16593.75 | P14: =P16-P13 -> 19700.1 | Q14: =Q16-Q13 -> 22480.416
A15: Other operating items | B15: 0 | C15: 0 | D15: 0 | E15: 0 | F15: 0 | G15: 0 | H15: 1353 | I15: 0 | J15: 0 | K15: 0 | M15: 0 | N15: 0 | O15: 0 | P15: 0 | Q15: 0
A16: Total operating expenses | B16: =SUM(B13:B15) -> 2129 | C16: =SUM(C13:C15) -> 2612 | D16: =SUM(D13:D15) -> 3367 | E16: =SUM(E13:E15) -> 3922 | F16: =SUM(F13:F15) -> 5864 | G16: =SUM(G13:G15) -> 7434 | H16: =SUM(H13:H15) -> 11132 | I16: =SUM(I13:I15) -> 11329 | ... K16: =SUM(K13:K15) -> 23076 | M16: =M11-M17 -> 49500 | N16: =N11-N17 -> 66093.75 | O16: =O11-O17 -> 82968.75 | P16: =P11-P17 -> 98500.5 | Q16: =Q11-Q17 -> 112402.08
A17: Operating income (EBIT) | B17: =B11-B16 -> 1934 | C17: =C11-C16 -> 3210 | D17: =D11-D16 -> 3804 | E17: =E11-E16 -> 2846 | F17: =F11-F16 -> 4532 | G17: =G11-G16 -> 10041 | H17: =H11-H16 -> 4224 | I17: =I11-I16 -> 32972 | ... K17: =K11-K16 -> 130387 | L17: 197579 | M17: =M8*M18 -> 279000 | N17: =N8*N18 -> 338906.25 | O17: =O8*O18 -> 388293.75 | P17: =P8*P18 -> 421879.5 | Q17: =Q8*Q18 -> 441579.6
A18: Operating margin | B18: =B17/B8 -> 0.27988423 | C18: =C17/C8 -> 0.3304509 | D18: =D17/D8 -> 0.32468419 | E18: =E17/E8 -> 0.26067045 | F18: =F17/F8 -> 0.27178411 | G18: =G17/G8 -> 0.37307721 | H18: =H17/H8 -> 0.15659524 | I18: =I17/I8 -> 0.54121664 | ... L18: =L17/L8 -> 0.65214048 | M18: =NVDA!C84 -> 0.62 | N18: =NVDA!D84 -> 0.6025 | O18: =NVDA!E84 -> 0.585 | P18: =NVDA!F84 -> 0.5675 | Q18: =NVDA!G84 -> 0.55
A19: Interest and other income, net | B19: -29 | C19: -14 | D19: 92 | E19: 124 | F19: -123 | G19: -100 | H19: -43 | I19: 846 | J19: 2573 | K19: 11063 | M19: =M8*$B$43 -> 4500 | N19: =N8*$B$43 -> 5625 | O19: =O8*$B$43 -> 6637.5 | P19: =P8*$B$43 -> 7434 | Q19: =Q8*$B$43 -> 8028.72
A20: Income before tax | B20: =B17+B19 -> 1905 | C20: =C17+C19 -> 3196 | D20: =D17+D19 -> 3896 | E20: =E17+E19 -> 2970 | F20: =F17+F19 -> 4409 | G20: =G17+G19 -> 9941 | H20: =H17+H19 -> 4181 | I20: =I17+I19 -> 33818 | ... K20: =K17+K19 -> 141450 | M20: =M17+M19 -> 283500 | N20: =N17+N19 -> 344531.25 | O20: =O17+O19 -> 394931.25 | P20: =P17+P19 -> 429313.5 | Q20: =Q17+Q19 -> 449608.32
A21: Income tax | B21: 239 | C21: 149 | D21: -245 | E21: 174 | F21: 77 | G21: 189 | H21: -187 | I21: 4058 | J21: 11146 | K21: 21383 | M21: =M20*$B$45 -> 42525 | N21: =N20*$B$45 -> 51679.688 | O21: =O20*$B$45 -> 59239.688 | P21: =P20*$B$45 -> 64397.025 | Q21: =Q20*$B$45 -> 67441.248
A22: Effective tax rate | B22: =B21/B20 -> 0.12545932 | C22: =C21/C20 -> 0.046620776 | D22: =D21/D20 -> -0.06288501 | E22: =E21/E20 -> 0.058585859 | F22: =F21/F20 -> 0.017464278 | G22: =G21/G20 -> 0.019012172 | H22: =H21/H20 -> -0.044726142 | I22: =I21/I20 -> 0.11999527 | ... K22: =K21/K20 -> 0.15117002 | M22: =M21/M20 -> 0.15 | N22: =N21/N20 -> 0.15 | O22: =O21/O20 -> 0.15 | P22: =P21/P20 -> 0.15 | Q22: =Q21/Q20 -> 0.15
A23: Net income | B23: =B20-B21 -> 1666 | C23: =C20-C21 -> 3047 | D23: =D20-D21 -> 4141 | E23: =E20-E21 -> 2796 | F23: =F20-F21 -> 4332 | G23: =G20-G21 -> 9752 | H23: =H20-H21 -> 4368 | I23: =I20-I21 -> 29760 | ... K23: =K20-K21 -> 120067 | L23: 192880 | M23: =M20-M21 -> 240975 | N23: =N20-N21 -> 292851.56 | O23: =O20-O21 -> 335691.56 | P23: =P20-P21 -> 364916.47 | Q23: =Q20-Q21 -> 382167.07
A24: Net margin | B24: =B23/B8 -> 0.24109986 | C24: =C23/C8 -> 0.31367099 | D24: =D23/D8 -> 0.35344828 | E24: =E23/E8 -> 0.25609086 | F24: =F23/F8 -> 0.2597901 | G24: =G23/G8 -> 0.3623393 | H24: =H23/H8 -> 0.16193371 | I24: =I23/I8 -> 0.48849348 | ... Q24: =Q23/Q8 -> 0.476
A25: Diluted shares (millions) | B25: 25960 | C25: 25280 | D25: 25000 | E25: 24720 | F25: 25100 | G25: 25350 | H25: 25070 | I25: 24940 | J25: 24804 | K25: 24514 | M25: =$K$25*(1+$B$44)^M$7 -> 24391.43 | N25: =$K$25*(1+$B$44)^N$7 -> 24269.473 | O25: =$K$25*(1+$B$44)^O$7 -> 24148.125 | P25: =$K$25*(1+$B$44)^P$7 -> 24027.385 | Q25: =$K$25*(1+$B$44)^Q$7 -> 23907.248
A26: Diluted EPS ($) | B26: =B23/B25 -> 0.064175655 | C26: =C23/C25 -> 0.12053006 | D26: =D23/D25 -> 0.16564 | E26: =E23/E25 -> 0.1131068 | F26: =F23/F25 -> 0.17258964 | G26: =G23/G25 -> 0.38469428 | H26: =H23/H25 -> 0.17423215 | I26: =I23/I25 -> 1.1932638 | ... K26: =K23/K25 -> 4.8978951 | L26: 7.91 | M26: =M23/M25 -> 9.8794946 | N26: =N23/N25 -> 12.066664 | O26: =O23/O25 -> 13.901351 | P26: =P23/P25 -> 15.187524 | Q26: =Q23/Q25 -> 15.985406
A27: EPS growth | C27: =C26/B26-1 -> 0.87812752 | D27: =D26/C26-1 -> 0.37426295 | E27: =E26/D26-1 -> -0.31715289 | F27: =F26/E26-1 -> 0.52589983 | G27: =G26/F26-1 -> 1.2289535 | H27: =H26/G26-1 -> -0.54708931 | I27: =I26/H26-1 -> 5.8487006 | J27: =J26/I26-1 -> 1.4623522 | K27: =K26/J26-1 -> 0.66695101 | M27: =M26/L26-1 -> 0.24898793 | N27: =N26/M26-1 -> 0.2213847 | O27: =O26/N26-1 -> 0.15204594 | P27: =P26/O26-1 -> 0.092521431 | Q27: =Q26/P26-1 -> 0.052535404
A28: Free cash flow | B28: 1496 | C28: 2909 | D28: 3143 | E28: 4272 | F28: 4694 | G28: 8132 | H28: 3808 | I28: 27021 | J28: 60853 | K28: 96676 | L28: 127006 | M28: =NVDA!C89*1000 -> 177862.5 | N28: =NVDA!D89*1000 -> 219653.61 | O28: =NVDA!E89*1000 -> 255788.51 | P28: =NVDA!F89*1000 -> 282395.59 | Q28: =NVDA!G89*1000 -> 300274.13
A29: Free cash flow margin | B29: =B28/B8 -> 0.21649783 | C29: =C28/C8 -> 0.29946469 | D29: =D28/D8 -> 0.26826562 | E29: =E28/E8 -> 0.39128045 | F29: =F28/F8 -> 0.28149925 | G29: =G28/G8 -> 0.30214758 | H29: =H28/H8 -> 0.14117298 | I29: =I28/I8 -> 0.44353436 | ... Q29: =Q28/Q8 -> 0.374
A30: Capital expenditure | B30: 176 | C30: 593 | D30: 600 | E30: 489 | F30: 1128 | G30: 976 | H30: 1833 | I30: 1069 | J30: 3236 | K30: 6042
A31: Capex as % of revenue | B31: =B30/B8 -> 0.025470333 | C31: =C30/C8 -> 0.061045913 | D31: =D30/D8 -> 0.051212018 | E31: =E30/E8 -> 0.044788423 | F31: =F30/F8 -> 0.067646177 | G31: =G30/G8 -> 0.036263655 | H31: =H30/H8 -> 0.067954326 | I31: =I30/I8 -> 0.017547027 | ... K31: =K30/K8 -> 0.027980254
A33: Integrity checks (history)
A34: Operating income as reported | B34: 1934 | C34: 3210 | D34: 3804 | E34: 2846 | F34: 4532 | G34: 10041 | H34: 4224 | I34: 32972 | J34: 81453 | K34: 130387
A35: Difference from calculated (should be 0) | B35: =B17-B34 -> 0 | C35: =C17-C34 -> 0 | D35: =D17-D34 -> 0 | E35: =E17-E34 -> 0 | F35: =F17-F34 -> 0 | G35: =G17-G34 -> 0 | H35: =H17-H34 -> 0 | I35: =I17-I34 -> 0 | ... K35: =K17-K34 -> 0
A36: Net income as reported | B36: 1666 | C36: 3047 | D36: 4141 | E36: 2796 | F36: 4332 | G36: 9752 | H36: 4368 | I36: 29760 | J36: 72880 | K36: 120067
A37: Difference from calculated (should be 0) | B37: =B23-B36 -> 0 | C37: =C23-C36 -> 0 | D37: =D23-D36 -> 0 | E37: =E23-E36 -> 0 | F37: =F23-F36 -> 0 | G37: =G23-G36 -> 0 | H37: =H23-H36 -> 0 | I37: =I23-I36 -> 0 | ... K37: =K23-K36 -> 0
A39: Forecast assumptions (edit the blue cells; revenue, operating margin and free cash flow come from the Base scenario)
A40: Gross margin, forecast year 1 | B40: 0.73
A41: Gross margin, forecast year 5 | B41: 0.69
A42: R&D as share of operating expenses | B42: 0.8
A43: Interest and other income, % of revenue | B43: 0.01
A44: Change in diluted shares per year | B44: -0.005
A45: Tax rate on profit before tax | B45: =NVDA!B11 -> 0.15
A48: Growth and margin summary
A49: Revenue CAGR, last 3 years | B49: =(K8/H8)^(1/3)-1 -> 1.0004509
A50: Revenue CAGR, last 5 years | B50: =(K8/F8)^(1/5)-1 -> 0.66898582
A51: Revenue CAGR, last 9 years | B51: =(K8/B8)^(1/9)-1 -> 0.46586697
A52: Revenue CAGR, latest 12 months to forecast year 5 | B52: =(Q8/L8)^(1/5)-1 -> 0.21520441
A53: Average operating margin, 10 years | B53: =AVERAGE(B18:K18) -> 0.37663551
A54: Operating margin, latest full year | B54: =K18 -> 0.60381684
A55: Operating margin, forecast year 5 | B55: =Q18 -> 0.55
A56: EPS CAGR, last 9 years | B56: =(K26/B26)^(1/9)-1 -> 0.61875875
A57: EPS CAGR, latest 12 months to forecast year 5 | B57: =(Q26/L26)^(1/5)-1 -> 0.15109042
A59: Sources: company earnings releases (fiscal-year results) for FY history; StockAnalysis.com for trailing twelve months. Forecast lines are analyst estimates, not company guidance.

Sheet META
A1: Meta Platforms (META): intrinsic value build (story, numbers, value)
A2: USD billions unless stated. Prices at close 18 Sep 2026. Blue = input, black = formula, yellow fill = key assumption.
A4: 1. Market data
A5: Share price ($) | B5: 665.75
A6: Market capitalisation ($bn) | B6: 1700
A7: Shares outstanding (bn) | B7: =B6/B5 -> 2.5535111
A8: Cash ($bn) | B8: 90.26
A9: Total debt ($bn) | B9: 112.32
A10: Revenue, last 12 months ($bn) | B10: 228.25
A11: Tax rate on operating profit | B11: 0.15
A13: 2. Cost of capital (build-up)
A14: Risk-free rate | B14: 0.0494
A15: Equity risk premium | B15: 0.045
A16: Raw beta | B16: 1.24
A17: Blume weight on raw beta | B17: 0.67
A18: Adjusted beta | B18: =B17*B16+(1-B17)*1 -> 1.1608
A19: Cost of equity | B19: =B14+B18*B15 -> 0.101636
A20: Pre-tax cost of debt | B20: 0.0575
A21: After-tax cost of debt | B21: =B20*(1-B11) -> 0.048875
A22: Equity weight (market cap / (market cap + debt)) | B22: =B6/(B6+B9) -> 0.93802419
A23: Debt weight | B23: =B9/(B6+B9) -> 0.06197581
A24: WACC (calculated) | B24: =B22*B19+B23*B21 -> 0.098366094
A25: WACC floor | B25: 0.08
A26: WACC cap | B26: 0.11
A27: WACC used | B27: =MEDIAN(B25,B24,B26) -> 0.098366094
A28: Terminal growth rate | B28: 0.03
A29: Growth fades to (years 6-10) | B29: 0.03
A31: 3. Story to numbers: scenario assumptions
A32: Driver | B32: Unit | C32: Bear | D32: Base | E32: Bull | F32: Market-implied
A33: Story: Bear | B33: Advertising growth cools to low single digits while AI spending keeps free cash flow thin; operating margin drifts down toward 28%.
A34: Story: Base | B34: Advertising keeps growing at a double-digit rate that fades to 8%; margin edges from 34% to 36% and cash conversion recovers from 55% to 75% as AI capital spending eases.
A35: Story: Bull | B35: AI lifts ad pricing and engagement: growth runs 18% fading to 10%, margin reaches 42% and cash conversion 85%.
A36: Story: Market-implied | B36: What today's price requires: the Base story with growth in years 2-5 scaled up until value per share equals the price (see the scale factor in F47).
A38: Year-1 revenue (next 12 months) | B38: $bn | C38: 255 | D38: 268 | E38: 280 | F38: =D38 -> 268
A39: Revenue growth, year 2 | B39: % | C39: 0.06 | D39: 0.14 | E39: 0.18 | F39: =D39*$F$47 -> 0.255122
A40: Revenue growth, year 3 | B40: % | C40: 0.04 | D40: 0.11 | E40: 0.15 | F40: =D40*$F$47 -> 0.200453
A41: Revenue growth, year 4 | B41: % | C41: 0.03 | D41: 0.09 | E41: 0.12 | F41: =D41*$F$47 -> 0.164007
A42: Revenue growth, year 5 | B42: % | C42: 0.03 | D42: 0.08 | E42: 0.1 | F42: =D42*$F$47 -> 0.145784
A43: Operating margin, year 1 | B43: % | C43: 0.3 | D43: 0.34 | E43: 0.38 | F43: =D43 -> 0.34
A44: Operating margin, year 5 (held to year 10) | B44: % | C44: 0.28 | D44: 0.36 | E44: 0.42 | F44: =D44 -> 0.36
A45: Cash conversion, year 1 (FCFF / after-tax operating profit) | B45: % | C45: 0.45 | D45: 0.55 | E45: 0.6 | F45: =D45 -> 0.55
A46: Cash conversion, year 5 (held to year 10) | B46: % | C46: 0.6 | D46: 0.75 | E46: 0.85 | F46: =D46 -> 0.75
A47: Growth scale factor (Market-implied only) | B47: x | C47: 1 | D47: 1 | E47: 1 | F47: 1.8223 | G47: Goal Seek F58 to equal B5 by changing F47
A49: 4. Valuation summary
A50: Item | B50: Unit | C50: Bear | D50: Base | E50: Bull | F50: Market-implied
A51: PV of FCFF, years 1-10 | B51: $bn | C51: =SUM(C77:L77) -> 245.53434 | D51: =SUM(C91:L91) -> 499.533 | E51: =SUM(C105:L105) -> 757.67636 | F51: =SUM(C119:L119) -> 671.96833
A52: Terminal value at year 10 | B52: $bn | C52: =L75*(1+$B$28)/($B$27-$B$28) -> 743.81447 | D52: =L89*(1+$B$28)/($B$27-$B$28) -> 1760.9277 | E52: =L103*(1+$B$28)/($B$27-$B$28) -> 2834.5243 | F52: =L117*(1+$B$28)/($B$27-$B$28) -> 2683.4381
A53: PV of terminal value | B53: $bn | C53: =C52*L76 -> 291.06731 | D53: =D52*L90 -> 689.08111 | E53: =E52*L104 -> 1109.1978 | F53: =F52*L118 -> 1050.0752
A54: Enterprise value (operating assets) | B54: $bn | C54: =C51+C53 -> 536.60166 | D54: =D51+D53 -> 1188.6141 | E54: =E51+E53 -> 1866.8742 | F54: =F51+F53 -> 1722.0435
A55: Plus: cash | B55: $bn | C55: =$B$8 -> 90.26 | D55: =$B$8 -> 90.26 | E55: =$B$8 -> 90.26 | F55: =$B$8 -> 90.26
A56: Less: debt | B56: $bn | C56: =-$B$9 -> -112.32 | D56: =-$B$9 -> -112.32 | E56: =-$B$9 -> -112.32 | F56: =-$B$9 -> -112.32
A57: Equity value | B57: $bn | C57: =C54+C55+C56 -> 514.54166 | D57: =D54+D55+D56 -> 1166.5541 | E57: =E54+E55+E56 -> 1844.8142 | F57: =F54+F55+F56 -> 1699.9835
A58: Value per share | B58: $ | C58: =C57/$B$7 -> 201.50359 | D58: =D57/$B$7 -> 456.84318 | E58: =E57/$B$7 -> 722.46178 | F58: =F57/$B$7 -> 665.74355
A59: Share price | B59: $ | C59: =$B$5 -> 665.75 | D59: =$B$5 -> 665.75 | E59: =$B$5 -> 665.75 | F59: =$B$5 -> 665.75
A60: Value versus price | B60: % | C60: =C58/C59-1 -> -0.69732844 | D60: =D58/D59-1 -> -0.3137917 | E60: =E58/E59-1 -> 0.085184805 | F60: =F58/F59-1 -> -9.6926313e-06
A61: Terminal value as % of enterprise value | B61: % | C61: =C53/C54 -> 0.54242716 | D61: =D53/D54 -> 0.57973492 | E61: =E53/E54 -> 0.59414707 | F61: =F53/F54 -> 0.60978435
A62: Terminal reinvestment rate (1 - cash conversion) | B62: % | C62: =1-L73 -> 0.4 | D62: =1-L87 -> 0.25 | E62: =1-L101 -> 0.15 | F62: =1-L115 -> 0.25
A63: Implied terminal return on capital (g / reinvestment rate) | B63: % | C63: =IF(C62>0,$B$28/C62,0) -> 0.075 | D63: =IF(D62>0,$B$28/D62,0) -> 0.12 | E63: =IF(E62>0,$B$28/E62,0) -> 0.2 | F63: =IF(F62>0,$B$28/F62,0) -> 0.12
A64: Revenue CAGR, last 12 months to year 5 | B64: % | C64: =(G68/$B$10)^(1/5)-1 -> 0.054942065 | D64: =(G82/$B$10)^(1/5)-1 -> 0.11830539 | E64: =(G96/$B$10)^(1/5)-1 -> 0.15448305 | F64: =(G110/$B$10)^(1/5)-1 -> 0.18730608
A65: 5. Cash-flow projections (FCFF) by scenario
A66: Bear scenario
A67: Year | C67: 1 | D67: 2 | E67: 3 | F67: 4 | G67: 5 | H67: 6 | I67: 7 | J67: 8 | K67: 9 | L67: 10
A68: Revenue ($bn) | C68: =C$38 -> 255 | D68: =C68*(1+D69) -> 270.3 | E68: =D68*(1+E69) -> 281.112 | F68: =E68*(1+F69) -> 289.54536 | G68: =F68*(1+G69) -> 298.23172 | H68: =G68*(1+H69) -> 307.17867 | I68: =H68*(1+I69) -> 316.39403 | J68: =I68*(1+J69) -> 325.88585 | K68: =J68*(1+K69) -> 335.66243 | L68: =K68*(1+L69) -> 345.7323
A69: Revenue growth | C69: =C68/$B$10-1 -> 0.11719606 | D69: =C$39 -> 0.06 | E69: =C$40 -> 0.04 | F69: =C$41 -> 0.03 | G69: =C$42 -> 0.03 | H69: =G69+($B$29-$G69)/5 -> 0.03 | I69: =H69+($B$29-$G69)/5 -> 0.03 | J69: =I69+($B$29-$G69)/5 -> 0.03 | K69: =J69+($B$29-$G69)/5 -> 0.03 | L69: =K69+($B$29-$G69)/5 -> 0.03
A70: Operating margin | C70: =C$43+(C$44-C$43)*MIN(C$67-1,4)/4 -> 0.3 | D70: =C$43+(C$44-C$43)*MIN(D$67-1,4)/4 -> 0.295 | E70: =C$43+(C$44-C$43)*MIN(E$67-1,4)/4 -> 0.29 | F70: =C$43+(C$44-C$43)*MIN(F$67-1,4)/4 -> 0.285 | G70: =C$43+(C$44-C$43)*MIN(G$67-1,4)/4 -> 0.28 | H70: =C$43+(C$44-C$43)*MIN(H$67-1,4)/4 -> 0.28 | I70: =C$43+(C$44-C$43)*MIN(I$67-1,4)/4 -> 0.28 | J70: =C$43+(C$44-C$43)*MIN(J$67-1,4)/4 -> 0.28 | K70: =C$43+(C$44-C$43)*MIN(K$67-1,4)/4 -> 0.28 | L70: =C$43+(C$44-C$43)*MIN(L$67-1,4)/4 -> 0.28
A71: Operating profit (EBIT) | C71: =C68*C70 -> 76.5 | D71: =D68*D70 -> 79.7385 | E71: =E68*E70 -> 81.52248 | F71: =F68*F70 -> 82.520428 | G71: =G68*G70 -> 83.504882 | H71: =H68*H70 -> 86.010028 | I71: =I68*I70 -> 88.590329 | J71: =J68*J70 -> 91.248039 | ... L71: =L68*L70 -> 96.805045
A72: After-tax operating profit | C72: =C71*(1-$B$11) -> 65.025 | D72: =D71*(1-$B$11) -> 67.777725 | E72: =E71*(1-$B$11) -> 69.294108 | F72: =F71*(1-$B$11) -> 70.142363 | G72: =G71*(1-$B$11) -> 70.97915 | H72: =H71*(1-$B$11) -> 73.108524 | I72: =I71*(1-$B$11) -> 75.30178 | J72: =J71*(1-$B$11) -> 77.560833 | ... L72: =L71*(1-$B$11) -> 82.284288
A73: Cash conversion | C73: =C$45+(C$46-C$45)*MIN(C$67-1,4)/4 -> 0.45 | D73: =C$45+(C$46-C$45)*MIN(D$67-1,4)/4 -> 0.4875 | E73: =C$45+(C$46-C$45)*MIN(E$67-1,4)/4 -> 0.525 | F73: =C$45+(C$46-C$45)*MIN(F$67-1,4)/4 -> 0.5625 | G73: =C$45+(C$46-C$45)*MIN(G$67-1,4)/4 -> 0.6 | H73: =C$45+(C$46-C$45)*MIN(H$67-1,4)/4 -> 0.6 | I73: =C$45+(C$46-C$45)*MIN(I$67-1,4)/4 -> 0.6 | J73: =C$45+(C$46-C$45)*MIN(J$67-1,4)/4 -> 0.6 | K73: =C$45+(C$46-C$45)*MIN(K$67-1,4)/4 -> 0.6 | L73: =C$45+(C$46-C$45)*MIN(L$67-1,4)/4 -> 0.6
A74: Reinvestment | C74: =C72*(1-C73) -> 35.76375 | D74: =D72*(1-D73) -> 34.736084 | E74: =E72*(1-E73) -> 32.914701 | F74: =F72*(1-F73) -> 30.687284 | G74: =G72*(1-G73) -> 28.39166 | H74: =H72*(1-H73) -> 29.24341 | I74: =I72*(1-I73) -> 30.120712 | J74: =J72*(1-J73) -> 31.024333 | ... L74: =L72*(1-L73) -> 32.913715
A75: Free cash flow to firm (FCFF) | C75: =C72-C74 -> 29.26125 | D75: =D72-D74 -> 33.041641 | E75: =E72-E74 -> 36.379407 | F75: =F72-F74 -> 39.455079 | G75: =G72-G74 -> 42.58749 | H75: =H72-H74 -> 43.865114 | I75: =I72-I74 -> 45.181068 | J75: =J72-J74 -> 46.5365 | ... L75: =L72-L74 -> 49.370573
A76: Discount factor | C76: =1/(1+$B$27)^C$67 -> 0.91044325 | D76: =1/(1+$B$27)^D$67 -> 0.82890692 | E76: =1/(1+$B$27)^E$67 -> 0.75467271 | F76: =1/(1+$B$27)^F$67 -> 0.68708668 | G76: =1/(1+$B$27)^G$67 -> 0.62555343 | H76: =1/(1+$B$27)^H$67 -> 0.5695309 | I76: =1/(1+$B$27)^I$67 -> 0.51852556 | J76: =1/(1+$B$27)^J$67 -> 0.4720881 | ... L76: =1/(1+$B$27)^L$67 -> 0.39131709
A77: Present value of FCFF | C77: =C75*C76 -> 26.640708 | D77: =D75*D76 -> 27.388445 | E77: =E75*E76 -> 27.454545 | F77: =F75*F76 -> 27.109059 | G77: =G75*G76 -> 26.64075 | H77: =H75*H76 -> 24.982538 | I77: =I75*I76 -> 23.427539 | J77: =J75*J76 -> 21.969328 | ... L77: =L75*L76 -> 19.319549
A80: Base scenario
A81: Year | C81: 1 | D81: 2 | E81: 3 | F81: 4 | G81: 5 | H81: 6 | I81: 7 | J81: 8 | K81: 9 | L81: 10
A82: Revenue ($bn) | C82: =D$38 -> 268 | D82: =C82*(1+D83) -> 305.52 | E82: =D82*(1+E83) -> 339.1272 | F82: =E82*(1+F83) -> 369.64865 | G82: =F82*(1+G83) -> 399.22054 | H82: =G82*(1+H83) -> 427.16598 | I82: =H82*(1+I83) -> 452.79594 | J82: =I82*(1+J83) -> 475.43573 | K82: =J82*(1+K83) -> 494.45316 | L82: =K82*(1+L83) -> 509.28676
A83: Revenue growth | C83: =C82/$B$10-1 -> 0.17415115 | D83: =D$39 -> 0.14 | E83: =D$40 -> 0.11 | F83: =D$41 -> 0.09 | G83: =D$42 -> 0.08 | H83: =G83+($B$29-$G83)/5 -> 0.07 | I83: =H83+($B$29-$G83)/5 -> 0.06 | J83: =I83+($B$29-$G83)/5 -> 0.05 | K83: =J83+($B$29-$G83)/5 -> 0.04 | L83: =K83+($B$29-$G83)/5 -> 0.03
A84: Operating margin | C84: =D$43+(D$44-D$43)*MIN(C$81-1,4)/4 -> 0.34 | D84: =D$43+(D$44-D$43)*MIN(D$81-1,4)/4 -> 0.345 | E84: =D$43+(D$44-D$43)*MIN(E$81-1,4)/4 -> 0.35 | F84: =D$43+(D$44-D$43)*MIN(F$81-1,4)/4 -> 0.355 | G84: =D$43+(D$44-D$43)*MIN(G$81-1,4)/4 -> 0.36 | H84: =D$43+(D$44-D$43)*MIN(H$81-1,4)/4 -> 0.36 | I84: =D$43+(D$44-D$43)*MIN(I$81-1,4)/4 -> 0.36 | J84: =D$43+(D$44-D$43)*MIN(J$81-1,4)/4 -> 0.36 | K84: =D$43+(D$44-D$43)*MIN(K$81-1,4)/4 -> 0.36 | L84: =D$43+(D$44-D$43)*MIN(L$81-1,4)/4 -> 0.36
A85: Operating profit (EBIT) | C85: =C82*C84 -> 91.12 | D85: =D82*D84 -> 105.4044 | E85: =E82*E84 -> 118.69452 | F85: =F82*F84 -> 131.22527 | G85: =G82*G84 -> 143.71939 | H85: =H82*H84 -> 153.77975 | I85: =I82*I84 -> 163.00654 | J85: =J82*J84 -> 171.15686 | ... L85: =L82*L84 -> 183.34323
A86: After-tax operating profit | C86: =C85*(1-$B$11) -> 77.452 | D86: =D85*(1-$B$11) -> 89.59374 | E86: =E85*(1-$B$11) -> 100.89034 | F86: =F85*(1-$B$11) -> 111.54148 | G86: =G85*(1-$B$11) -> 122.16149 | H86: =H85*(1-$B$11) -> 130.71279 | I86: =I85*(1-$B$11) -> 138.55556 | J86: =J85*(1-$B$11) -> 145.48333 | ... L86: =L85*(1-$B$11) -> 155.84175
A87: Cash conversion | C87: =D$45+(D$46-D$45)*MIN(C$81-1,4)/4 -> 0.55 | D87: =D$45+(D$46-D$45)*MIN(D$81-1,4)/4 -> 0.6 | E87: =D$45+(D$46-D$45)*MIN(E$81-1,4)/4 -> 0.65 | F87: =D$45+(D$46-D$45)*MIN(F$81-1,4)/4 -> 0.7 | G87: =D$45+(D$46-D$45)*MIN(G$81-1,4)/4 -> 0.75 | H87: =D$45+(D$46-D$45)*MIN(H$81-1,4)/4 -> 0.75 | I87: =D$45+(D$46-D$45)*MIN(I$81-1,4)/4 -> 0.75 | J87: =D$45+(D$46-D$45)*MIN(J$81-1,4)/4 -> 0.75 | K87: =D$45+(D$46-D$45)*MIN(K$81-1,4)/4 -> 0.75 | L87: =D$45+(D$46-D$45)*MIN(L$81-1,4)/4 -> 0.75
A88: Reinvestment | C88: =C86*(1-C87) -> 34.8534 | D88: =D86*(1-D87) -> 35.837496 | E88: =E86*(1-E87) -> 35.31162 | F88: =F86*(1-F87) -> 33.462444 | G88: =G86*(1-G87) -> 30.540371 | H88: =H86*(1-H87) -> 32.678197 | I88: =I86*(1-I87) -> 34.638889 | J88: =J86*(1-J87) -> 36.370834 | ... L88: =L86*(1-L87) -> 38.960437
A89: Free cash flow to firm (FCFF) | C89: =C86-C88 -> 42.5986 | D89: =D86-D88 -> 53.756244 | E89: =E86-E88 -> 65.578722 | F89: =F86-F88 -> 78.079036 | G89: =G86-G88 -> 91.621114 | H89: =H86-H88 -> 98.034592 | I89: =I86-I88 -> 103.91667 | J89: =J86-J88 -> 109.1125 | ... L89: =L86-L88 -> 116.88131
A90: Discount factor | C90: =1/(1+$B$27)^C$81 -> 0.91044325 | D90: =1/(1+$B$27)^D$81 -> 0.82890692 | E90: =1/(1+$B$27)^E$81 -> 0.75467271 | F90: =1/(1+$B$27)^F$81 -> 0.68708668 | G90: =1/(1+$B$27)^G$81 -> 0.62555343 | H90: =1/(1+$B$27)^H$81 -> 0.5695309 | I90: =1/(1+$B$27)^I$81 -> 0.51852556 | J90: =1/(1+$B$27)^J$81 -> 0.4720881 | ... L90: =1/(1+$B$27)^L$81 -> 0.39131709
A91: Present value of FCFF | C91: =C89*C90 -> 38.783608 | D91: =D89*D90 -> 44.558922 | E91: =E89*E90 -> 49.490472 | F91: =F89*F90 -> 53.647065 | G91: =G89*G90 -> 57.313902 | H91: =H89*H90 -> 55.833729 | I91: =I89*I90 -> 53.883449 | J91: =J89*J90 -> 51.510713 | ... L91: =L89*L90 -> 45.737655
A94: Bull scenario
A95: Year | C95: 1 | D95: 2 | E95: 3 | F95: 4 | G95: 5 | H95: 6 | I95: 7 | J95: 8 | K95: 9 | L95: 10
A96: Revenue ($bn) | C96: =E$38 -> 280 | D96: =C96*(1+D97) -> 330.4 | E96: =D96*(1+E97) -> 379.96 | F96: =E96*(1+F97) -> 425.5552 | G96: =F96*(1+G97) -> 468.11072 | H96: =G96*(1+H97) -> 508.36824 | I96: =H96*(1+I97) -> 544.97076 | J96: =I96*(1+J97) -> 576.57906 | K96: =J96*(1+K97) -> 601.94854 | L96: =K96*(1+L97) -> 620.00699
A97: Revenue growth | C97: =C96/$B$10-1 -> 0.22672508 | D97: =E$39 -> 0.18 | E97: =E$40 -> 0.15 | F97: =E$41 -> 0.12 | G97: =E$42 -> 0.1 | H97: =G97+($B$29-$G97)/5 -> 0.086 | I97: =H97+($B$29-$G97)/5 -> 0.072 | J97: =I97+($B$29-$G97)/5 -> 0.058 | K97: =J97+($B$29-$G97)/5 -> 0.044 | L97: =K97+($B$29-$G97)/5 -> 0.03
A98: Operating margin | C98: =E$43+(E$44-E$43)*MIN(C$95-1,4)/4 -> 0.38 | D98: =E$43+(E$44-E$43)*MIN(D$95-1,4)/4 -> 0.39 | E98: =E$43+(E$44-E$43)*MIN(E$95-1,4)/4 -> 0.4 | F98: =E$43+(E$44-E$43)*MIN(F$95-1,4)/4 -> 0.41 | G98: =E$43+(E$44-E$43)*MIN(G$95-1,4)/4 -> 0.42 | H98: =E$43+(E$44-E$43)*MIN(H$95-1,4)/4 -> 0.42 | I98: =E$43+(E$44-E$43)*MIN(I$95-1,4)/4 -> 0.42 | J98: =E$43+(E$44-E$43)*MIN(J$95-1,4)/4 -> 0.42 | K98: =E$43+(E$44-E$43)*MIN(K$95-1,4)/4 -> 0.42 | L98: =E$43+(E$44-E$43)*MIN(L$95-1,4)/4 -> 0.42
A99: Operating profit (EBIT) | C99: =C96*C98 -> 106.4 | D99: =D96*D98 -> 128.856 | E99: =E96*E98 -> 151.984 | F99: =F96*F98 -> 174.47763 | G99: =G96*G98 -> 196.6065 | H99: =H96*H98 -> 213.51466 | I99: =I96*I98 -> 228.88772 | J99: =J96*J98 -> 242.1632 | ... L99: =L96*L98 -> 260.40294
A100: After-tax operating profit | C100: =C99*(1-$B$11) -> 90.44 | D100: =D99*(1-$B$11) -> 109.5276 | E100: =E99*(1-$B$11) -> 129.1864 | F100: =F99*(1-$B$11) -> 148.30599 | G100: =G99*(1-$B$11) -> 167.11553 | H100: =H99*(1-$B$11) -> 181.48746 | I100: =I99*(1-$B$11) -> 194.55456 | J100: =J99*(1-$B$11) -> 205.83872 | ... L100: =L99*(1-$B$11) -> 221.3425
A101: Cash conversion | C101: =E$45+(E$46-E$45)*MIN(C$95-1,4)/4 -> 0.6 | D101: =E$45+(E$46-E$45)*MIN(D$95-1,4)/4 -> 0.6625 | E101: =E$45+(E$46-E$45)*MIN(E$95-1,4)/4 -> 0.725 | F101: =E$45+(E$46-E$45)*MIN(F$95-1,4)/4 -> 0.7875 | G101: =E$45+(E$46-E$45)*MIN(G$95-1,4)/4 -> 0.85 | H101: =E$45+(E$46-E$45)*MIN(H$95-1,4)/4 -> 0.85 | I101: =E$45+(E$46-E$45)*MIN(I$95-1,4)/4 -> 0.85 | J101: =E$45+(E$46-E$45)*MIN(J$95-1,4)/4 -> 0.85 | K101: =E$45+(E$46-E$45)*MIN(K$95-1,4)/4 -> 0.85 | L101: =E$45+(E$46-E$45)*MIN(L$95-1,4)/4 -> 0.85
A102: Reinvestment | C102: =C100*(1-C101) -> 36.176 | D102: =D100*(1-D101) -> 36.965565 | E102: =E100*(1-E101) -> 35.52626 | F102: =F100*(1-F101) -> 31.515022 | G102: =G100*(1-G101) -> 25.067329 | H102: =H100*(1-H101) -> 27.223119 | I102: =I100*(1-I101) -> 29.183184 | J102: =J100*(1-J101) -> 30.875809 | ... L102: =L100*(1-L101) -> 33.201375
A103: Free cash flow to firm (FCFF) | C103: =C100-C102 -> 54.264 | D103: =D100-D102 -> 72.562035 | E103: =E100-E102 -> 93.66014 | F103: =F100-F102 -> 116.79096 | G103: =G100-G102 -> 142.0482 | H103: =H100-H102 -> 154.26434 | I103: =I100-I102 -> 165.37138 | J103: =J100-J102 -> 174.96292 | ... L103: =L100-L102 -> 188.14112
A104: Discount factor | C104: =1/(1+$B$27)^C$95 -> 0.91044325 | D104: =1/(1+$B$27)^D$95 -> 0.82890692 | E104: =1/(1+$B$27)^E$95 -> 0.75467271 | F104: =1/(1+$B$27)^F$95 -> 0.68708668 | G104: =1/(1+$B$27)^G$95 -> 0.62555343 | H104: =1/(1+$B$27)^H$95 -> 0.5695309 | I104: =1/(1+$B$27)^I$95 -> 0.51852556 | J104: =1/(1+$B$27)^J$95 -> 0.4720881 | ... L104: =1/(1+$B$27)^L$95 -> 0.39131709
A105: Present value of FCFF | C105: =C103*C104 -> 49.404293 | D105: =D103*D104 -> 60.147173 | E105: =E103*E104 -> 70.682752 | F105: =F103*F104 -> 80.245516 | G105: =G103*G104 -> 88.858737 | H105: =H103*H104 -> 87.85831 | I105: =I103*I104 -> 85.749286 | J105: =J103*J104 -> 82.597911 | ... L105: =L103*L104 -> 73.622837
A108: Market-implied scenario
A109: Year | C109: 1 | D109: 2 | E109: 3 | F109: 4 | G109: 5 | H109: 6 | I109: 7 | J109: 8 | K109: 9 | L109: 10
A110: Revenue ($bn) | C110: =F$38 -> 268 | D110: =C110*(1+D111) -> 336.3727 | E110: =D110*(1+E111) -> 403.79961 | F110: =E110*(1+F111) -> 470.02558 | G110: =F110*(1+G111) -> 538.54778 | H110: =G110*(1+H111) -> 604.58839 | I110: =H110*(1+I111) -> 664.72704 | J110: =I110*(1+J111) -> 715.45475 | K110: =J110*(1+K111) -> 753.48604 | L110: =K110*(1+L111) -> 776.09062
A111: Revenue growth | C111: =C110/$B$10-1 -> 0.17415115 | D111: =F$39 -> 0.255122 | E111: =F$40 -> 0.200453 | F111: =F$41 -> 0.164007 | G111: =F$42 -> 0.145784 | H111: =G111+($B$29-$G111)/5 -> 0.1226272 | I111: =H111+($B$29-$G111)/5 -> 0.0994704 | J111: =I111+($B$29-$G111)/5 -> 0.0763136 | K111: =J111+($B$29-$G111)/5 -> 0.0531568 | L111: =K111+($B$29-$G111)/5 -> 0.03
...

Sheet META_PnL
A1: Meta Platforms: income statement, 10 years of history and 5 forecast periods
A2: USD millions except per-share data. Fiscal years end 31 December. Forecast columns are 12-month periods from the valuation date (NTM = next twelve months, to Sep-27) and link to the Base scenario on the META sheet. Blue = input, black = formula, green = link.
A4: Period | B4: FY2016 | C4: FY2017 | D4: FY2018 | E4: FY2019 | F4: FY2020 | G4: FY2021 | H4: FY2022 | I4: FY2023 | J4: FY2024 | K4: FY2025 | L4: TTM Jun-26 | M4: NTM | N4: Year 2 | O4: Year 3 | P4: Year 4 | Q4: Year 5
A5: Period end | B5: Dec-16 | C5: Dec-17 | D5: Dec-18 | E5: Dec-19 | F5: Dec-20 | G5: Dec-21 | H5: Dec-22 | I5: Dec-23 | J5: Dec-24 | K5: Dec-25 | M5: Sep-27 | N5: Sep-28 | O5: Sep-29 | P5: Sep-30 | Q5: Sep-31
A6: Basis | B6: Actual | C6: Actual | D6: Actual | E6: Actual | F6: Actual | G6: Actual | H6: Actual | I6: Actual | J6: Actual | K6: Actual | L6: Latest 12m | M6: Base forecast | N6: Base forecast | O6: Base forecast | P6: Base forecast | Q6: Base forecast
A7: Forecast year | M7: 1 | N7: 2 | O7: 3 | P7: 4 | Q7: 5
A8: Revenue | B8: 27638 | C8: 40653 | D8: 55838 | E8: 70697 | F8: 85965 | G8: 117929 | H8: 116609 | I8: 134902 | J8: 164501 | K8: 200966 | L8: 228247 | M8: =META!C82*1000 -> 268000 | N8: =META!D82*1000 -> 305520 | O8: =META!E82*1000 -> 339127.2 | P8: =META!F82*1000 -> 369648.65 | Q8: =META!G82*1000 -> 399220.54
A9: Revenue growth | C9: =C8/B8-1 -> 0.47090962 | D9: =D8/C8-1 -> 0.37352717 | E9: =E8/D8-1 -> 0.2661091 | F9: =F8/E8-1 -> 0.2159639 | G9: =G8/F8-1 -> 0.37182574 | H9: =H8/G8-1 -> -0.011193176 | I9: =I8/H8-1 -> 0.15687468 | J9: =J8/I8-1 -> 0.21941113 | K9: =K8/J8-1 -> 0.22167038 | M9: =M8/L8-1 -> 0.17416658 | N9: =N8/M8-1 -> 0.14 | O9: =O8/N8-1 -> 0.11 | P9: =P8/O8-1 -> 0.09 | Q9: =Q8/P8-1 -> 0.08
A10: Cost of revenue | B10: 3789 | C10: 5454 | D10: 9355 | E10: 12770 | F10: 16692 | G10: 22649 | H10: 25249 | I10: 25959 | J10: 30161 | K10: 36175 | M10: =M8-M11 -> 58960 | N10: =N8-N11 -> 67978.2 | O10: =O8-O11 -> 76303.62 | P10: =P8-P11 -> 84095.067 | Q10: =Q8-Q11 -> 91820.724
A11: Gross profit | B11: =B8-B10 -> 23849 | C11: =C8-C10 -> 35199 | D11: =D8-D10 -> 46483 | E11: =E8-E10 -> 57927 | F11: =F8-F10 -> 69273 | G11: =G8-G10 -> 95280 | H11: =H8-H10 -> 91360 | I11: =I8-I10 -> 108943 | ... K11: =K8-K10 -> 164791 | L11: 186586 | M11: =M8*M12 -> 209040 | N11: =N8*N12 -> 237541.8 | O11: =O8*O12 -> 262823.58 | P11: =P8*P12 -> 285553.58 | Q11: =Q8*Q12 -> 307399.82
A12: Gross margin | B12: =B11/B8 -> 0.86290614 | C12: =C11/C8 -> 0.86584016 | D12: =D11/D8 -> 0.83246176 | E12: =E11/E8 -> 0.81936999 | F12: =F11/F8 -> 0.80582795 | G12: =G11/G8 -> 0.80794376 | H12: =H11/H8 -> 0.78347297 | I12: =I11/I8 -> 0.80757142 | ... L12: =L11/L8 -> 0.81747405 | M12: =$B$40+($B$41-$B$40)*(M$7-1)/4 -> 0.78 | N12: =$B$40+($B$41-$B$40)*(N$7-1)/4 -> 0.7775 | O12: =$B$40+($B$41-$B$40)*(O$7-1)/4 -> 0.775 | P12: =$B$40+($B$41-$B$40)*(P$7-1)/4 -> 0.7725 | Q12: =$B$40+($B$41-$B$40)*(Q$7-1)/4 -> 0.77
A13: Research and development | B13: 5919 | C13: 7754 | D13: 10273 | E13: 13600 | F13: 18447 | G13: 24655 | H13: 35338 | I13: 38483 | J13: 43873 | K13: 57372 | M13: =M16*$B$42 -> 82544 | N13: =N16*$B$42 -> 92496.18 | O13: =O16*$B$42 -> 100890.34 | P13: =P16*$B$42 -> 108029.82 | Q13: =Q16*$B$42 -> 114576.29
A14: Sales, general and administrative | B14: =3772+1731 -> 5503 | C14: =4725+2517 -> 7242 | D14: =7846+3451 -> 11297 | E14: =9876+10465 -> 20341 | F14: =11591+6564 -> 18155 | G14: =14043+9829 -> 23872 | H14: =15262+11816 -> 27078 | I14: =12301+11408 -> 23709 | J14: =11347+9740 -> 21087 | K14: =11991+12152 -> 24143 | M14: =M16-M13 -> 35376 | N14: =N16-N13 -> 39641.22 | O14: =O16-O13 -> 43238.718 | P14: =P16-P13 -> 46298.493 | Q14: =Q16-Q13 -> 49104.126
A15: Other operating items | B15: 0 | C15: 0 | D15: 0 | E15: 0 | F15: 0 | G15: 0 | H15: 0 | I15: 0 | J15: 0 | K15: 0 | M15: 0 | N15: 0 | O15: 0 | P15: 0 | Q15: 0
A16: Total operating expenses | B16: =SUM(B13:B15) -> 11422 | C16: =SUM(C13:C15) -> 14996 | D16: =SUM(D13:D15) -> 21570 | E16: =SUM(E13:E15) -> 33941 | F16: =SUM(F13:F15) -> 36602 | G16: =SUM(G13:G15) -> 48527 | H16: =SUM(H13:H15) -> 62416 | I16: =SUM(I13:I15) -> 62192 | ... K16: =SUM(K13:K15) -> 81515 | M16: =M11-M17 -> 117920 | N16: =N11-N17 -> 132137.4 | O16: =O11-O17 -> 144129.06 | P16: =P11-P17 -> 154328.31 | Q16: =Q11-Q17 -> 163680.42
A17: Operating income (EBIT) | B17: =B11-B16 -> 12427 | C17: =C11-C16 -> 20203 | D17: =D11-D16 -> 24913 | E17: =E11-E16 -> 23986 | F17: =F11-F16 -> 32671 | G17: =G11-G16 -> 46753 | H17: =H11-H16 -> 28944 | I17: =I11-I16 -> 46751 | ... K17: =K11-K16 -> 83276 | L17: 86926 | M17: =M8*M18 -> 91120 | N17: =N8*N18 -> 105404.4 | O17: =O8*O18 -> 118694.52 | P17: =P8*P18 -> 131225.27 | Q17: =Q8*Q18 -> 143719.39
A18: Operating margin | B18: =B17/B8 -> 0.44963456 | C18: =C17/C8 -> 0.49696209 | D18: =D17/D8 -> 0.44616569 | E18: =E17/E8 -> 0.33927889 | F18: =F17/F8 -> 0.38005002 | G18: =G17/G8 -> 0.39645041 | H18: =H17/H8 -> 0.24821412 | I18: =I17/I8 -> 0.34655528 | ... L18: =L17/L8 -> 0.38084181 | M18: =META!C84 -> 0.34 | N18: =META!D84 -> 0.345 | O18: =META!E84 -> 0.35 | P18: =META!F84 -> 0.355 | Q18: =META!G84 -> 0.36
A19: Interest and other income, net | B19: 91 | C19: 391 | D19: 448 | E19: 826 | F19: 509 | G19: 531 | H19: -125 | I19: 677 | J19: 1283 | K19: 2656 | M19: =M8*$B$43 -> 2144 | N19: =N8*$B$43 -> 2444.16 | O19: =O8*$B$43 -> 2713.0176 | P19: =P8*$B$43 -> 2957.1892 | Q19: =Q8*$B$43 -> 3193.7643
A20: Income before tax | B20: =B17+B19 -> 12518 | C20: =C17+C19 -> 20594 | D20: =D17+D19 -> 25361 | E20: =E17+E19 -> 24812 | F20: =F17+F19 -> 33180 | G20: =G17+G19 -> 47284 | H20: =H17+H19 -> 28819 | I20: =I17+I19 -> 47428 | ... K20: =K17+K19 -> 85932 | M20: =M17+M19 -> 93264 | N20: =N17+N19 -> 107848.56 | O20: =O17+O19 -> 121407.54 | P20: =P17+P19 -> 134182.46 | Q20: =Q17+Q19 -> 146913.16
A21: Income tax | B21: 2301 | C21: 4660 | D21: 3249 | E21: 6327 | F21: 4034 | G21: 7914 | H21: 5619 | I21: 8330 | J21: 8303 | K21: 25474 | M21: =M20*$B$45 -> 13989.6 | N21: =N20*$B$45 -> 16177.284 | O21: =O20*$B$45 -> 18211.131 | P21: =P20*$B$45 -> 20127.369 | Q21: =Q20*$B$45 -> 22036.974
A22: Effective tax rate | B22: =B21/B20 -> 0.18381531 | C22: =C21/C20 -> 0.2262795 | D22: =D21/D20 -> 0.12811009 | E22: =E21/E20 -> 0.25499758 | F22: =F21/F20 -> 0.12157926 | G22: =G21/G20 -> 0.16737163 | H22: =H21/H20 -> 0.19497554 | I22: =I21/I20 -> 0.17563465 | ... K22: =K21/K20 -> 0.2964437 | M22: =M21/M20 -> 0.15 | N22: =N21/N20 -> 0.15 | O22: =O21/O20 -> 0.15 | P22: =P21/P20 -> 0.15 | Q22: =Q21/Q20 -> 0.15
A23: Net income | B23: =B20-B21 -> 10217 | C23: =C20-C21 -> 15934 | D23: =D20-D21 -> 22112 | E23: =E20-E21 -> 18485 | F23: =F20-F21 -> 29146 | G23: =G20-G21 -> 39370 | H23: =H20-H21 -> 23200 | I23: =I20-I21 -> 39098 | ... K23: =K20-K21 -> 60458 | L23: 68098 | M23: =M20-M21 -> 79274.4 | N23: =N20-N21 -> 91671.276 | O23: =O20-O21 -> 103196.41 | P23: =P20-P21 -> 114055.09 | Q23: =Q20-Q21 -> 124876.18
A24: Net margin | B24: =B23/B8 -> 0.36967219 | C24: =C23/C8 -> 0.39195139 | D24: =D23/D8 -> 0.39600272 | E24: =E23/E8 -> 0.26146795 | F24: =F23/F8 -> 0.33904496 | G24: =G23/G8 -> 0.33384494 | H24: =H23/H8 -> 0.19895548 | I24: =I23/I8 -> 0.28982521 | ... Q24: =Q23/Q8 -> 0.3128
A25: Diluted shares (millions) | B25: 2925 | C25: 2956 | D25: 2921 | E25: 2876 | F25: 2888 | G25: 2859 | H25: 2702 | I25: 2629 | J25: 2614 | K25: 2574 | M25: =$K$25*(1+$B$44)^M$7 -> 2574 | N25: =$K$25*(1+$B$44)^N$7 -> 2574 | O25: =$K$25*(1+$B$44)^O$7 -> 2574 | P25: =$K$25*(1+$B$44)^P$7 -> 2574 | Q25: =$K$25*(1+$B$44)^Q$7 -> 2574
A26: Diluted EPS ($) | B26: =B23/B25 -> 3.4929915 | C26: =C23/C25 -> 5.3903924 | D26: =D23/D25 -> 7.5700103 | E26: =E23/E25 -> 6.4273296 | F26: =F23/F25 -> 10.092105 | G26: =G23/G25 -> 13.770549 | H26: =H23/H25 -> 8.5862324 | I26: =I23/I25 -> 14.871814 | ... K26: =K23/K25 -> 23.487956 | L26: 26.54 | M26: =M23/M25 -> 30.798135 | N26: =N23/N25 -> 35.614326 | O26: =O23/O25 -> 40.091844 | P26: =P23/P25 -> 44.310447 | Q26: =Q23/Q25 -> 48.514446
A27: EPS growth | C27: =C26/B26-1 -> 0.54320229 | D27: =D26/C26-1 -> 0.40435235 | E27: =E26/D26-1 -> -0.15094836 | F27: =F26/E26-1 -> 0.57018635 | G27: =G26/F26-1 -> 0.36448727 | H27: =H26/G26-1 -> -0.37647858 | I27: =I26/H26-1 -> 0.73205355 | J27: =J26/I26-1 -> 0.60411894 | K27: =K26/J26-1 -> -0.015434281 | M27: =M26/L26-1 -> 0.16044217 | N27: =N26/M26-1 -> 0.15637931 | O27: =O26/N26-1 -> 0.12572238 | P27: =P26/O26-1 -> 0.10522346 | Q27: =Q26/P26-1 -> 0.094876033
A28: Free cash flow | B28: 11617 | C28: 17483 | D28: 15359 | E28: 20656 | F28: 23028 | G28: 38439 | H28: 18439 | I28: 43010 | J28: 52103 | K28: 43585 | L28: 41070 | M28: =META!C89*1000 -> 42598.6 | N28: =META!D89*1000 -> 53756.244 | O28: =META!E89*1000 -> 65578.722 | P28: =META!F89*1000 -> 78079.036 | Q28: =META!G89*1000 -> 91621.114
A29: Free cash flow margin | B29: =B28/B8 -> 0.42032709 | C29: =C28/C8 -> 0.43005436 | D29: =D28/D8 -> 0.27506358 | E29: =E28/E8 -> 0.29217647 | F29: =F28/F8 -> 0.26787646 | G29: =G28/G8 -> 0.32595036 | H29: =H28/H8 -> 0.15812673 | I29: =I28/I8 -> 0.31882404 | ... Q29: =Q28/Q8 -> 0.2295
A30: Capital expenditure | B30: 4491 | C30: 6733 | D30: 13915 | E30: 15650 | F30: 15115 | G30: 19240 | H30: 31431 | I30: 28100 | J30: 37256 | K30: 72220
A31: Capex as % of revenue | B31: =B30/B8 -> 0.16249367 | C31: =C30/C8 -> 0.16562123 | D31: =D30/D8 -> 0.24920305 | E31: =E30/E8 -> 0.22136724 | F31: =F30/F8 -> 0.17582737 | G31: =G30/G8 -> 0.16314901 | H31: =H30/H8 -> 0.2695418 | I31: =I30/I8 -> 0.20829936 | ... K31: =K30/K8 -> 0.35936427
A33: Integrity checks (history)
A34: Operating income as reported | B34: 12427 | C34: 20203 | D34: 24913 | E34: 23986 | F34: 32671 | G34: 46753 | H34: 28944 | I34: 46751 | J34: 69380 | K34: 83276
A35: Difference from calculated (should be 0) | B35: =B17-B34 -> 0 | C35: =C17-C34 -> 0 | D35: =D17-D34 -> 0 | E35: =E17-E34 -> 0 | F35: =F17-F34 -> 0 | G35: =G17-G34 -> 0 | H35: =H17-H34 -> 0 | I35: =I17-I34 -> 0 | ... K35: =K17-K34 -> 0
A36: Net income as reported | B36: 10217 | C36: 15934 | D36: 22112 | E36: 18485 | F36: 29146 | G36: 39370 | H36: 23200 | I36: 39098 | J36: 62360 | K36: 60458
A37: Difference from calculated (should be 0) | B37: =B23-B36 -> 0 | C37: =C23-C36 -> 0 | D37: =D23-D36 -> 0 | E37: =E23-E36 -> 0 | F37: =F23-F36 -> 0 | G37: =G23-G36 -> 0 | H37: =H23-H36 -> 0 | I37: =I23-I36 -> 0 | ... K37: =K23-K36 -> 0
A39: Forecast assumptions (edit the blue cells; revenue, operating margin and free cash flow come from the Base scenario)
A40: Gross margin, forecast year 1 | B40: 0.78
A41: Gross margin, forecast year 5 | B41: 0.77
A42: R&D as share of operating expenses | B42: 0.7
A43: Interest and other income, % of revenue | B43: 0.008
A44: Change in diluted shares per year | B44: 0
A45: Tax rate on profit before tax | B45: =META!B11 -> 0.15
A48: Growth and margin summary
A49: Revenue CAGR, last 3 years | B49: =(K8/H8)^(1/3)-1 -> 0.19893831
A50: Revenue CAGR, last 5 years | B50: =(K8/F8)^(1/5)-1 -> 0.18511415
A51: Revenue CAGR, last 9 years | B51: =(K8/B8)^(1/9)-1 -> 0.24662292
A52: Revenue CAGR, latest 12 months to forecast year 5 | B52: =(Q8/L8)^(1/5)-1 -> 0.11830833
A53: Average operating margin, 10 years | B53: =AVERAGE(B18:K18) -> 0.393945
A54: Operating margin, latest full year | B54: =K18 -> 0.41437855
A55: Operating margin, forecast year 5 | B55: =Q18 -> 0.36
A56: EPS CAGR, last 9 years | B56: =(K26/B26)^(1/9)-1 -> 0.23583604
A57: EPS CAGR, latest 12 months to forecast year 5 | B57: =(Q26/L26)^(1/5)-1 -> 0.12822062
A59: Sources: company earnings releases (fiscal-year results) for FY history; StockAnalysis.com for trailing twelve months. Forecast lines are analyst estimates, not company guidance.

Sheet PE_Benchmarks
A1: P/E ratio versus market and industry benchmarks
A2: Prices at close 18 Sep 2026. Multiples come from different providers and methods, so use them as guides rather than exact comparisons. Blue = input, black = formula, green = link.
A4: 1. Company multiples
A5: Item | B5: NVDA | C5: META | D5: Source and note
A6: Share price ($) | B6: =NVDA!B5 -> 222.27 | C6: =META!B5 -> 665.75 | D6: Company sheets
A7: Trailing EPS, last 12 months ($) | B7: =NVDA_PnL!L26 -> 7.91 | C7: =META_PnL!L26 -> 26.54 | D7: P&L sheets (StockAnalysis.com TTM)
A8: Trailing P/E (calculated) | B8: =B6/B7 -> 28.099874 | C8: =C6/C7 -> 25.084778 | D8: Price ÷ trailing EPS
A9: Trailing P/E (StockAnalysis.com) | B9: 28.11 | C9: 25.09 | D9: StockAnalysis.com statistics pages, 19 Sep 2026
A10: Forward P/E (consensus-based) | B10: 18.45 | C10: 20.57 | D10: StockAnalysis.com statistics pages, 19 Sep 2026; based on analyst consensus estimates
A11: Implied consensus forward EPS ($) | B11: =B6/B10 -> 12.047154 | C11: =C6/C10 -> 32.365095 | D11: Price ÷ forward P/E
A12: PEG ratio | B12: 0.35 | C12: 1.02 | D12: StockAnalysis.com; forward P/E divided by expected earnings growth
A13: EV/EBITDA | B13: 26.55 | C13: 15.67 | D13: StockAnalysis.com
A14: Price/sales | B14: 17.72 | C14: 7.43 | D14: StockAnalysis.com
A16: 2. Benchmarks (one value each)
A17: Item | B17: Value | D17: Source and note
A18: S&P 500 forward 12-month P/E | B18: 19.1 | D18: FactSet Earnings Insight, 18 Sep 2026
A19: S&P 500 forward P/E, 5-year average | B19: 19.8 | D19: FactSet Earnings Insight, 18 Sep 2026
A20: S&P 500 forward P/E, 10-year average | B20: 19 | D20: FactSet Earnings Insight, 18 Sep 2026
A21: S&P 500 trailing 12-month P/E | B21: 25.5 | D21: FactSet Earnings Insight, 18 Sep 2026
A22: Semiconductors: trailing P/E | B22: 61.52 | D22: iShares Semiconductor ETF (SOXX) fund P/E, 16 Sep 2026. Forward P/E not published on the fact sheet.
A23: Communication services: trailing P/E | B23: 15.5 | D23: Communication Services Select Sector SPDR (XLC) fund P/E, 17 Sep 2026. Includes telecom and legacy media, which trade at lower multiples than Meta.
A24: Communication services: forward P/E | B24: 12.63 | D24: XLC fund forward P/E, 17 Sep 2026
A26: Industry benchmark used for each company | B26: NVDA | C26: META
A27: Industry trailing P/E | B27: =B22 -> 61.52 | C27: =B23 -> 15.5 | D27: NVDA: semiconductors. META: communication services.
A28: Industry forward P/E | B28: n/a | C28: =B24 -> 12.63
A30: 3. Premium or discount
A31: Item | B31: NVDA | C31: META | D31: Source and note
A32: Trailing P/E versus S&P 500 | B32: =B9/$B$21-1 -> 0.10235294 | C32: =C9/$B$21-1 -> -0.016078431
A33: Trailing P/E versus industry | B33: =B9/B27-1 -> -0.54307542 | C33: =C9/C27-1 -> 0.61870968
A34: Forward P/E versus S&P 500 | B34: =B10/$B$18-1 -> -0.034031414 | C34: =C10/$B$18-1 -> 0.076963351
A35: Forward P/E versus S&P 500 10-year average | B35: =B10/$B$20-1 -> -0.028947368 | C35: =C10/$B$20-1 -> 0.082631579
A36: Forward P/E versus industry | B36: =IF(ISNUMBER(B28),B10/B28-1,"n/a") -> n/a | C36: =IF(ISNUMBER(C28),C10/C28-1,"n/a") -> 0.62866192
A38: 4. What our Base value implies for the P/E
A39: Item | B39: NVDA | C39: META | D39: Source and note
A40: Base value per share ($) | B40: =NVDA!D58 -> 141.62346 | C40: =META!D58 -> 456.84318 | D40: DCF Base scenario
A41: P/E implied by Base value (on consensus forward EPS) | B41: =B40/B11 -> 11.75576 | C41: =C40/C11 -> 14.115305 | D41: Base value ÷ implied consensus forward EPS
A42: versus S&P 500 forward P/E | B42: =B41/$B$18-1 -> -0.38451519 | C42: =C41/$B$18-1 -> -0.26097881
A43: Model EPS, next 12 months (Base) ($) | B43: =NVDA_PnL!M26 -> 9.8794946 | C43: =META_PnL!M26 -> 30.798135 | D43: P&L sheets, first forecast period
A44: P/E at today's price on model EPS | B44: =B6/B43 -> 22.498115 | C44: =C6/C43 -> 21.616569 | D44: Price ÷ model NTM EPS
A45: Consensus forward EPS versus model NTM EPS | B45: =B11/B43-1 -> 0.21941 | C45: =C11/C43-1 -> 0.050878392 | D45: Positive means the market's earnings expectation is above our Base year 1
A46: P/E implied by Base value (on trailing EPS) | B46: =B40/B7 -> 17.904356 | C46: =C40/C7 -> 17.213383 | D46: Base value ÷ trailing 12-month EPS
A48: Method note: company P/Es come from a data aggregator, the S&P 500 from FactSet, and industry P/Es from fund fact sheets. Definitions differ, so differences of a few points are not meaningful.

Sheet Macro
A1: Macro backdrop: indicators chosen for each company
A2: Indicators are selected by how the company earns money: consumer and inflation gauges for advertising-led Meta, capital-spending, chip-demand and policy gauges for Nvidia. Readings are as published; the direction column is the analyst's read.
A4: 1. Relevance matrix (how strongly each indicator drives the company)
B5: Indicator | C5: NVDA | D5: META
B6: Consumer sentiment | C6: Low | D6: High
B7: Inflation and energy costs | C7: Med | D7: High
B8: Disposable income and spending | C8: Low | D8: High
B9: Interest rates and bond yields | C9: High | D9: High
B10: Hyperscaler capital spending | C10: High | D10: Med
B11: Global chip demand and supply | C11: High | D11: Med
B12: Trade and export policy | C12: High | D12: Low
A14: 2. NVIDIA: selected indicators. Net read: Demand is a tailwind; the price of money is the headwind.
A15: Company | B15: Indicator | C15: Latest reading | D15: Period | E15: Direction | F15: Why it matters for this company | G15: Source
A16: NVDA | B16: Hyperscaler capital spending | C16: $720–745B planned for 2026 by Alphabet, Amazon, Meta and Microsoft | D16: Guidance as of 18 Aug 2026 | E16: Tailwind | F16: These four are Nvidia's largest customers: their budgets are Nvidia's revenue pool. Funding is stretched: Meta's Q2 free cash flow was $0.8B and Amazon's trailing free cash flow is negative. | G16: https://www.tmtfinance.com/intel/2026-hyperscaler-capex-tops-us700bn-analysis
A17: NVDA | B17: Global chip demand | C17: Sales of $146.8B in July, up 135% on a year ago, the 17th straight monthly rise | D17: Jul 2026, 3-month average | E17: Tailwind | F17: A broad upswing in chip demand supports volumes and pricing across the supply chain. The Americas grew fastest (+171%). | G17: https://www.semiconductors.org/global-semiconductor-sales-increase-6-4-month-to-month-in-july/
A18: NVDA | B18: Interest rates | C18: Fed funds 3.75–4.00% after a 25 bp hike; 10-year Treasury at 4.94% | D18: 16–17 Sep 2026 | E18: Headwind | F18: Higher yields raise the discount rate. With a beta above 2, Nvidia's calculated cost of capital is 13.1%; we cap it at 11%, so the result is generous. | G18: https://www.advisorperspectives.com/dshort/updates/2026/09/16/feds-interest-rate-decision-september-16-2026
A19: NVDA | B19: Inflation and energy costs | C19: CPI +3.4% year on year; energy +16.3% | D19: Aug 2026 | E19: Mixed | F19: Power is a large running cost for AI data centres, which squeezes customers' returns on each chip. The direct effect on Nvidia's own costs is small. | G19: https://www.bls.gov/news.release/cpi.nr0.htm
A20: NVDA | B20: Trade and export policy | C20: US licences allow limited H200 sales to China; press reports say 25% of that revenue goes to the US government | D20: Feb–Apr 2026 | E20: Mixed | F20: China access is partial and politically dependent. It is upside to our Base case only if volumes grow; it is not assumed in the numbers. | G20: https://www.bloomberg.com/news/articles/2026-02-26/nvidia-gets-us-license-for-small-amount-of-h200-exports-to-china
A21: NVDA | B21: Consumer demand (gaming and edge) | C21: Edge computing is 7.5% of revenue; consumer sentiment 47.8 | D21: Q2 FY2027; Sep 2026 | E21: Low relevance | F21: Consumer indicators matter little here because about 92% of revenue comes from data-centre customers. | G21: https://www.academic-capital.com/2026/09/september-2026-university-of-michigan.html
A23: 3. Meta Platforms: selected indicators. Net read: The consumer backdrop is soft, and rates and AI input costs add pressure.
A24: Company | B24: Indicator | C24: Latest reading | D24: Period | E24: Direction | F24: Why it matters for this company | G24: Source
A25: META | B25: Consumer sentiment | C25: 47.8, down from 51.7 in August and 55.1 a year ago | D25: Sep 2026, preliminary | E25: Headwind | F25: Advertisers cut budgets when their own customers turn cautious. Meta's ad revenue follows retail and consumer spending closely. | G25: https://www.academic-capital.com/2026/09/september-2026-university-of-michigan.html
A26: META | B26: Inflation | C26: CPI +3.4% (core +2.4%); gasoline +27.4%; PCE prices +3.7% | D26: Aug and Jul 2026 | E26: Headwind | F26: Fuel-led inflation squeezes household budgets and the marketing budgets of consumer brands, Meta's core advertisers. | G26: https://www.bls.gov/news.release/cpi.nr0.htm
A27: META | B27: Disposable income and spending | C27: Real disposable income +0.4% in July; real spending up less than 0.1%; saving rate 3.0% | D27: Jul 2026, month on month | E27: Mixed | F27: Incomes are still growing, but a saving rate of 3.0% leaves little cushion if spending pulls back. | G27: https://www.bea.gov/news/2026/personal-income-and-outlays-july-2026
A28: META | B28: Interest rates | C28: Fed funds 3.75–4.00%; 10-year Treasury at 4.94% | D28: 16–17 Sep 2026 | E28: Headwind | F28: Raises the discount rate (Meta's rises to 9.8% in our model) and the cost of the debt funding AI spending: Meta added $24.9B of new debt. | G28: https://www.advisorperspectives.com/dshort/updates/2026/09/16/feds-interest-rate-decision-september-16-2026
A29: META | B29: AI input costs (chips, power) | C29: 2026 capex plan $130–145B; global chip sales +135% on a year ago | D29: Aug and Jul 2026 | E29: Headwind | F29: Raw materials for Meta are compute and energy. Strong chip demand competes with Meta for supply and keeps prices firm, which weighs on free cash flow. | G29: https://www.tmtfinance.com/intel/2026-hyperscaler-capex-tops-us700bn-analysis
A30: META | B30: Ad demand so far | C30: Ad impressions +14% and price per ad +12% | D30: Q2 2026, year on year | E30: Tailwind | F30: The company's own data shows no visible damage yet from weak sentiment. This is the indicator to watch for change. | G30: https://investor.atmeta.com/investor-news/press-release-details/2026/Meta-Reports-Second-Quarter-2026-Results/default.aspx
A32: Cost of capital link: the risk-free rate on the company sheets is the 10-year Treasury yield above (4.94%).

Sheet BBS_Score
A1: BBS Score: Brand-to-Balance-Sheet scorecard
A2: Each pillar is scored 1-10 by the analyst (blue) except Valuation Gap, which is formula-driven from the DCF. Total = weighted average x 10 (0-100).
A4: Pillar scores
A5: Pillar | B5: NVDA | C5: META | D5: Weight | E5: Evidence: NVIDIA | F5: Evidence: Meta
A6: Brand Power | B6: 8 | C6: 7 | D6: 0.2 | E6: 75% gross margin (pricing power); customers are a few very large buyers. | F6: 3.60B daily users (+3%); price per ad +12%; youth-safety trials flagged as a possible material loss.
A7: Growth Engine | B7: 10 | C7: 8 | D7: 0.2 | E7: Q2 FY27 revenue +106% YoY; next quarter guided to $108B. | F7: Q2 2026 revenue +28% YoY; next quarter guided to $61-64B.
A8: Profit Quality | B8: 10 | C8: 6 | D8: 0.2 | E8: 65% operating margin, 92% ROIC, $127B TTM free cash flow. | F8: 38% TTM operating margin but 31% in Q2 (43% a year ago); about $41B TTM free cash flow.
A9: Balance-Sheet Strength | B9: 9 | C9: 4 | D9: 0.2 | E9: Net cash about $24B; about $26B returned to shareholders in Q2. | F9: Debt exceeds cash by about $22B; Q2 free cash flow $0.8B after $31B capex; no buybacks in Q2.
A10: Valuation Gap (formula) | B10: =MAX(1,MIN(10,ROUND(6+10*(NVDA!D58/NVDA!B5-1),0))) -> 2 | C10: =MAX(1,MIN(10,ROUND(6+10*(META!D58/META!B5-1),0))) -> 3 | D10: 0.2 | E10: 6 = fairly priced; each 10 points of margin of safety (Base value versus price) moves the score by one point.
A11: Weights must total 100% | D11: =SUM(D6:D10) -> 1
A13: BBS Score (0-100) | B13: =SUMPRODUCT(B6:B10,$D$6:$D$10)/SUM($D$6:$D$10)*10 -> 78 | C13: =SUMPRODUCT(C6:C10,$D$6:$D$10)/SUM($D$6:$D$10)*10 -> 56
A14: Band | B14: =IF(B13>=80,"Exceptional",IF(B13>=65,"Strong",IF(B13>=50,"Mixed","Weak"))) -> Strong | C14: =IF(C13>=80,"Exceptional",IF(C13>=65,"Strong",IF(C13>=50,"Mixed","Weak"))) -> Mixed
